{"number":629,"start":1675257645257.2,"entries":[{"name":"https://quic.totto.page/simple.html","entryType":"navigation","startTime":0,"duration":58.799999952316284,"initiatorType":"navigation","nextHopProtocol":"h3","renderBlockingStatus":"blocking","workerStart":0,"redirectStart":0,"redirectEnd":0,"fetchStart":0.2999999523162842,"domainLookupStart":1.7999999523162842,"domainLookupEnd":2.799999952316284,"connectStart":2.799999952316284,"connectEnd":20.899999976158142,"secureConnectionStart":3.0999999046325684,"requestStart":21.299999952316284,"responseStart":22.699999928474426,"responseEnd":48.299999952316284,"transferSize":473,"encodedBodySize":173,"decodedBodySize":173,"responseStatus":0,"serverTiming":[],"unloadEventStart":0,"unloadEventEnd":0,"domInteractive":58.299999952316284,"domContentLoadedEventStart":58.299999952316284,"domContentLoadedEventEnd":58.299999952316284,"domComplete":58.799999952316284,"loadEventStart":58.799999952316284,"loadEventEnd":58.799999952316284,"type":"navigate","redirectCount":0,"activationStart":0}]}