{"number":686,"har":{"log":{"version":"1.2","creator":{"name":"chrome-har","version":"0.11.12","comment":"https://github.com/sitespeedio/chrome-har"},"pages":[{"id":"page_1","startedDateTime":"2023-02-01T15:31:55.248Z","title":"https://quic.totto.page/single.html","pageTimings":{}}],"entries":[{"cache":{},"startedDateTime":"2023-02-01T15:31:55.250Z","_requestId":"29F69449A38C33D071557A24BE06A8E1","_initialPriority":"VeryHigh","_priority":"VeryHigh","pageref":"page_1","request":{"method":"GET","url":"https://quic.totto.page/single.html","queryString":[],"headersSize":-1,"bodySize":0,"cookies":[],"headers":[{"name":"Upgrade-Insecure-Requests","value":"1"},{"name":"User-Agent","value":"Mozilla/5.0 (X11; Linux x86_64) AppleWebKit/537.36 (KHTML, like Gecko) HeadlessChrome/109.0.5414.74 Safari/537.36"}],"httpVersion":"h3"},"time":46.352000000000004,"_initiator_detail":"{\"type\":\"other\"}","_initiator_type":"other","response":{"httpVersion":"h3","redirectURL":"","status":200,"statusText":"","content":{"mimeType":"text/html","size":2567},"headersSize":-1,"bodySize":2684,"cookies":[],"headers":[{"name":"accept-ranges","value":"bytes"},{"name":"content-length","value":"2567"},{"name":"content-type","value":"text/html"},{"name":"date","value":"Wed, 01 Feb 2023 15:31:55 GMT"},{"name":"etag","value":"\"63cac5c8-a07\""},{"name":"last-modified","value":"Fri, 20 Jan 2023 16:48:08 GMT"},{"name":"server","value":"nginx/1.23.4"}],"_transferSize":2684},"connection":"0","serverIPAddress":"10.10.0.102","timings":{"blocked":0.831,"dns":1.308,"connect":18.452,"send":0.38,"wait":22.227,"receive":3.154,"ssl":18.452,"_queued":1.437},"_requestTime":823783.598183},{"cache":{},"startedDateTime":"2023-02-01T15:31:55.300Z","_requestId":"3504271.2","_initialPriority":"VeryHigh","_priority":"VeryHigh","pageref":"page_1","request":{"method":"GET","url":"https://quic.totto.page/css/4k.css","queryString":[],"headersSize":-1,"bodySize":0,"cookies":[],"headers":[{"name":"sec-ch-ua","value":""},{"name":"Referer","value":"https://quic.totto.page/single.html"},{"name":"sec-ch-ua-mobile","value":"?0"},{"name":"User-Agent","value":"Mozilla/5.0 (X11; Linux x86_64) AppleWebKit/537.36 (KHTML, like Gecko) HeadlessChrome/109.0.5414.74 Safari/537.36"},{"name":"sec-ch-ua-platform","value":""}],"httpVersion":"h3"},"time":45.866,"_initiator_detail":"{\"type\":\"parser\",\"url\":\"https://quic.totto.page/single.html\",\"lineNumber\":5,\"columnNumber\":54}","_initiator_type":"parser","_initiator":"https://quic.totto.page/single.html","_initiator_line":6,"response":{"httpVersion":"h3","redirectURL":"","status":200,"statusText":"","content":{"mimeType":"text/css","size":4220},"headersSize":-1,"bodySize":4337,"cookies":[],"headers":[{"name":"date","value":"Wed, 01 Feb 2023 15:31:55 GMT"},{"name":"last-modified","value":"Fri, 13 Jan 2023 13:00:52 GMT"},{"name":"server","value":"nginx/1.23.4"},{"name":"accept-ranges","value":"bytes"},{"name":"etag","value":"\"63c15604-107c\""},{"name":"content-length","value":"4220"},{"name":"content-type","value":"text/css"}],"_transferSize":4337},"connection":"0","serverIPAddress":"10.10.0.102","timings":{"blocked":1.49,"dns":-1,"connect":-1,"send":0.566,"wait":24.059,"receive":19.751,"ssl":-1,"_queued":0.69},"_requestTime":823783.648561},{"cache":{},"startedDateTime":"2023-02-01T15:31:55.301Z","_requestId":"3504271.3","_initialPriority":"VeryHigh","_priority":"VeryHigh","pageref":"page_1","request":{"method":"GET","url":"https://quic.totto.page/css/8k.css","queryString":[],"headersSize":-1,"bodySize":0,"cookies":[],"headers":[{"name":"sec-ch-ua","value":""},{"name":"Referer","value":"https://quic.totto.page/single.html"},{"name":"sec-ch-ua-mobile","value":"?0"},{"name":"User-Agent","value":"Mozilla/5.0 (X11; Linux x86_64) AppleWebKit/537.36 (KHTML, like Gecko) HeadlessChrome/109.0.5414.74 Safari/537.36"},{"name":"sec-ch-ua-platform","value":""}],"httpVersion":"h3"},"time":74.64699999999999,"_initiator_detail":"{\"type\":\"parser\",\"url\":\"https://quic.totto.page/single.html\",\"lineNumber\":6,\"columnNumber\":54}","_initiator_type":"parser","_initiator":"https://quic.totto.page/single.html","_initiator_line":7,"response":{"httpVersion":"h3","redirectURL":"","status":200,"statusText":"","content":{"mimeType":"text/css","size":8422},"headersSize":-1,"bodySize":8539,"cookies":[],"headers":[{"name":"date","value":"Wed, 01 Feb 2023 15:31:55 GMT"},{"name":"last-modified","value":"Fri, 13 Jan 2023 13:00:52 GMT"},{"name":"server","value":"nginx/1.23.4"},{"name":"accept-ranges","value":"bytes"},{"name":"etag","value":"\"63c15604-20e6\""},{"name":"content-length","value":"8422"},{"name":"content-type","value":"text/css"}],"_transferSize":8539},"connection":"0","serverIPAddress":"10.10.0.102","timings":{"blocked":4.802,"dns":-1,"connect":-1,"send":0.445,"wait":31.009,"receive":38.391,"ssl":-1,"_queued":1.212},"_requestTime":823783.649527},{"cache":{},"startedDateTime":"2023-02-01T15:31:55.303Z","_requestId":"3504271.4","_initialPriority":"VeryHigh","_priority":"VeryHigh","pageref":"page_1","request":{"method":"GET","url":"https://quic.totto.page/css/12k.css","queryString":[],"headersSize":-1,"bodySize":0,"cookies":[],"headers":[{"name":"sec-ch-ua","value":""},{"name":"Referer","value":"https://quic.totto.page/single.html"},{"name":"sec-ch-ua-mobile","value":"?0"},{"name":"User-Agent","value":"Mozilla/5.0 (X11; Linux x86_64) AppleWebKit/537.36 (KHTML, like Gecko) HeadlessChrome/109.0.5414.74 Safari/537.36"},{"name":"sec-ch-ua-platform","value":""}],"httpVersion":"h3"},"time":104.19200000000001,"_initiator_detail":"{\"type\":\"parser\",\"url\":\"https://quic.totto.page/single.html\",\"lineNumber\":7,\"columnNumber\":55}","_initiator_type":"parser","_initiator":"https://quic.totto.page/single.html","_initiator_line":8,"response":{"httpVersion":"h3","redirectURL":"","status":200,"statusText":"","content":{"mimeType":"text/css","size":12624},"headersSize":-1,"bodySize":12742,"cookies":[],"headers":[{"name":"date","value":"Wed, 01 Feb 2023 15:31:55 GMT"},{"name":"last-modified","value":"Fri, 13 Jan 2023 13:00:52 GMT"},{"name":"server","value":"nginx/1.23.4"},{"name":"accept-ranges","value":"bytes"},{"name":"etag","value":"\"63c15604-3150\""},{"name":"content-length","value":"12624"},{"name":"content-type","value":"text/css"}],"_transferSize":12742},"connection":"0","serverIPAddress":"10.10.0.102","timings":{"blocked":9.69,"dns":-1,"connect":-1,"send":0.437,"wait":29.019,"receive":65.046,"ssl":-1,"_queued":2.492},"_requestTime":823783.65121},{"cache":{},"startedDateTime":"2023-02-01T15:31:55.305Z","_requestId":"3504271.5","_initialPriority":"VeryHigh","_priority":"VeryHigh","pageref":"page_1","request":{"method":"GET","url":"https://quic.totto.page/css/16k.css","queryString":[],"headersSize":-1,"bodySize":0,"cookies":[],"headers":[{"name":"sec-ch-ua","value":""},{"name":"Referer","value":"https://quic.totto.page/single.html"},{"name":"sec-ch-ua-mobile","value":"?0"},{"name":"User-Agent","value":"Mozilla/5.0 (X11; Linux x86_64) AppleWebKit/537.36 (KHTML, like Gecko) HeadlessChrome/109.0.5414.74 Safari/537.36"},{"name":"sec-ch-ua-platform","value":""}],"httpVersion":"h3"},"time":183.59300000000002,"_initiator_detail":"{\"type\":\"parser\",\"url\":\"https://quic.totto.page/single.html\",\"lineNumber\":8,\"columnNumber\":55}","_initiator_type":"parser","_initiator":"https://quic.totto.page/single.html","_initiator_line":9,"response":{"httpVersion":"h3","redirectURL":"","status":200,"statusText":"","content":{"mimeType":"text/css","size":16826},"headersSize":-1,"bodySize":16946,"cookies":[],"headers":[{"name":"date","value":"Wed, 01 Feb 2023 15:31:55 GMT"},{"name":"last-modified","value":"Fri, 13 Jan 2023 13:00:52 GMT"},{"name":"server","value":"nginx/1.23.4"},{"name":"accept-ranges","value":"bytes"},{"name":"etag","value":"\"63c15604-41ba\""},{"name":"content-length","value":"16826"},{"name":"content-type","value":"text/css"}],"_transferSize":16946},"connection":"0","serverIPAddress":"10.10.0.102","timings":{"blocked":11.899,"dns":-1,"connect":-1,"send":0.398,"wait":24.188,"receive":147.108,"ssl":-1,"_queued":3.984},"_requestTime":823783.653064},{"cache":{},"startedDateTime":"2023-02-01T15:31:55.305Z","_requestId":"3504271.6","_initialPriority":"VeryHigh","_priority":"VeryHigh","pageref":"page_1","request":{"method":"GET","url":"https://quic.totto.page/css/20k.css","queryString":[],"headersSize":-1,"bodySize":0,"cookies":[],"headers":[{"name":"sec-ch-ua","value":""},{"name":"Referer","value":"https://quic.totto.page/single.html"},{"name":"sec-ch-ua-mobile","value":"?0"},{"name":"User-Agent","value":"Mozilla/5.0 (X11; Linux x86_64) AppleWebKit/537.36 (KHTML, like Gecko) HeadlessChrome/109.0.5414.74 Safari/537.36"},{"name":"sec-ch-ua-platform","value":""}],"httpVersion":"h3"},"time":270.154,"_initiator_detail":"{\"type\":\"parser\",\"url\":\"https://quic.totto.page/single.html\",\"lineNumber\":9,\"columnNumber\":55}","_initiator_type":"parser","_initiator":"https://quic.totto.page/single.html","_initiator_line":10,"response":{"httpVersion":"h3","redirectURL":"","status":200,"statusText":"","content":{"mimeType":"text/css","size":21028},"headersSize":-1,"bodySize":21148,"cookies":[],"headers":[{"name":"date","value":"Wed, 01 Feb 2023 15:31:55 GMT"},{"name":"last-modified","value":"Fri, 13 Jan 2023 13:00:52 GMT"},{"name":"server","value":"nginx/1.23.4"},{"name":"accept-ranges","value":"bytes"},{"name":"etag","value":"\"63c15604-5224\""},{"name":"content-length","value":"21028"},{"name":"content-type","value":"text/css"}],"_transferSize":21148},"connection":"0","serverIPAddress":"10.10.0.102","timings":{"blocked":12.052,"dns":-1,"connect":-1,"send":0.478,"wait":27.384,"receive":230.24,"ssl":-1,"_queued":4.357},"_requestTime":823783.653813},{"cache":{},"startedDateTime":"2023-02-01T15:31:55.307Z","_requestId":"3504271.7","_initialPriority":"VeryHigh","_priority":"VeryHigh","pageref":"page_1","request":{"method":"GET","url":"https://quic.totto.page/css/24k.css","queryString":[],"headersSize":-1,"bodySize":0,"cookies":[],"headers":[{"name":"sec-ch-ua","value":""},{"name":"Referer","value":"https://quic.totto.page/single.html"},{"name":"sec-ch-ua-mobile","value":"?0"},{"name":"User-Agent","value":"Mozilla/5.0 (X11; Linux x86_64) AppleWebKit/537.36 (KHTML, like Gecko) HeadlessChrome/109.0.5414.74 Safari/537.36"},{"name":"sec-ch-ua-platform","value":""}],"httpVersion":"h3"},"time":336.997,"_initiator_detail":"{\"type\":\"parser\",\"url\":\"https://quic.totto.page/single.html\",\"lineNumber\":10,\"columnNumber\":55}","_initiator_type":"parser","_initiator":"https://quic.totto.page/single.html","_initiator_line":11,"response":{"httpVersion":"h3","redirectURL":"","status":200,"statusText":"","content":{"mimeType":"text/css","size":25232},"headersSize":-1,"bodySize":25352,"cookies":[],"headers":[{"name":"date","value":"Wed, 01 Feb 2023 15:31:55 GMT"},{"name":"last-modified","value":"Fri, 13 Jan 2023 13:00:52 GMT"},{"name":"server","value":"nginx/1.23.4"},{"name":"accept-ranges","value":"bytes"},{"name":"etag","value":"\"63c15604-6290\""},{"name":"content-length","value":"25232"},{"name":"content-type","value":"text/css"}],"_transferSize":25352},"connection":"0","serverIPAddress":"10.10.0.102","timings":{"blocked":11.189,"dns":-1,"connect":-1,"send":0.367,"wait":35.395,"receive":290.046,"ssl":-1,"_queued":5.578},"_requestTime":823783.655385},{"cache":{},"startedDateTime":"2023-02-01T15:31:55.310Z","_requestId":"3504271.8","_initialPriority":"VeryHigh","_priority":"VeryHigh","pageref":"page_1","request":{"method":"GET","url":"https://quic.totto.page/css/28k.css","queryString":[],"headersSize":-1,"bodySize":0,"cookies":[],"headers":[{"name":"sec-ch-ua","value":""},{"name":"Referer","value":"https://quic.totto.page/single.html"},{"name":"sec-ch-ua-mobile","value":"?0"},{"name":"User-Agent","value":"Mozilla/5.0 (X11; Linux x86_64) AppleWebKit/537.36 (KHTML, like Gecko) HeadlessChrome/109.0.5414.74 Safari/537.36"},{"name":"sec-ch-ua-platform","value":""}],"httpVersion":"h3"},"time":445.612,"_initiator_detail":"{\"type\":\"parser\",\"url\":\"https://quic.totto.page/single.html\",\"lineNumber\":11,\"columnNumber\":55}","_initiator_type":"parser","_initiator":"https://quic.totto.page/single.html","_initiator_line":12,"response":{"httpVersion":"h3","redirectURL":"","status":200,"statusText":"","content":{"mimeType":"text/css","size":29434},"headersSize":-1,"bodySize":29554,"cookies":[],"headers":[{"name":"date","value":"Wed, 01 Feb 2023 15:31:55 GMT"},{"name":"last-modified","value":"Fri, 13 Jan 2023 13:00:52 GMT"},{"name":"server","value":"nginx/1.23.4"},{"name":"accept-ranges","value":"bytes"},{"name":"etag","value":"\"63c15604-72fa\""},{"name":"content-length","value":"29434"},{"name":"content-type","value":"text/css"}],"_transferSize":29554},"connection":"0","serverIPAddress":"10.10.0.102","timings":{"blocked":9.249,"dns":-1,"connect":-1,"send":0.384,"wait":35.792,"receive":400.187,"ssl":-1,"_queued":7.772},"_requestTime":823783.657925},{"cache":{},"startedDateTime":"2023-02-01T15:31:55.310Z","_requestId":"3504271.9","_initialPriority":"VeryHigh","_priority":"VeryHigh","pageref":"page_1","request":{"method":"GET","url":"https://quic.totto.page/css/32k.css","queryString":[],"headersSize":-1,"bodySize":0,"cookies":[],"headers":[{"name":"sec-ch-ua","value":""},{"name":"Referer","value":"https://quic.totto.page/single.html"},{"name":"sec-ch-ua-mobile","value":"?0"},{"name":"User-Agent","value":"Mozilla/5.0 (X11; Linux x86_64) AppleWebKit/537.36 (KHTML, like Gecko) HeadlessChrome/109.0.5414.74 Safari/537.36"},{"name":"sec-ch-ua-platform","value":""}],"httpVersion":"h3"},"time":558.336,"_initiator_detail":"{\"type\":\"parser\",\"url\":\"https://quic.totto.page/single.html\",\"lineNumber\":12,\"columnNumber\":55}","_initiator_type":"parser","_initiator":"https://quic.totto.page/single.html","_initiator_line":13,"response":{"httpVersion":"h3","redirectURL":"","status":200,"statusText":"","content":{"mimeType":"text/css","size":33636},"headersSize":-1,"bodySize":33756,"cookies":[],"headers":[{"name":"date","value":"Wed, 01 Feb 2023 15:31:55 GMT"},{"name":"last-modified","value":"Fri, 13 Jan 2023 13:00:52 GMT"},{"name":"server","value":"nginx/1.23.4"},{"name":"accept-ranges","value":"bytes"},{"name":"etag","value":"\"63c15604-8364\""},{"name":"content-length","value":"33636"},{"name":"content-type","value":"text/css"}],"_transferSize":33756},"connection":"0","serverIPAddress":"10.10.0.102","timings":{"blocked":9.201,"dns":-1,"connect":-1,"send":0.34,"wait":52.681,"receive":496.114,"ssl":-1,"_queued":8.024},"_requestTime":823783.658542},{"cache":{},"startedDateTime":"2023-02-01T15:31:55.311Z","_requestId":"3504271.10","_initialPriority":"VeryHigh","_priority":"VeryHigh","pageref":"page_1","request":{"method":"GET","url":"https://quic.totto.page/css/36k.css","queryString":[],"headersSize":-1,"bodySize":0,"cookies":[],"headers":[{"name":"sec-ch-ua","value":""},{"name":"Referer","value":"https://quic.totto.page/single.html"},{"name":"sec-ch-ua-mobile","value":"?0"},{"name":"User-Agent","value":"Mozilla/5.0 (X11; Linux x86_64) AppleWebKit/537.36 (KHTML, like Gecko) HeadlessChrome/109.0.5414.74 Safari/537.36"},{"name":"sec-ch-ua-platform","value":""}],"httpVersion":"h3"},"time":649.6959999999999,"_initiator_detail":"{\"type\":\"parser\",\"url\":\"https://quic.totto.page/single.html\",\"lineNumber\":13,\"columnNumber\":55}","_initiator_type":"parser","_initiator":"https://quic.totto.page/single.html","_initiator_line":14,"response":{"httpVersion":"h3","redirectURL":"","status":200,"statusText":"","content":{"mimeType":"text/css","size":37838},"headersSize":-1,"bodySize":37958,"cookies":[],"headers":[{"name":"date","value":"Wed, 01 Feb 2023 15:31:55 GMT"},{"name":"last-modified","value":"Fri, 13 Jan 2023 13:00:52 GMT"},{"name":"server","value":"nginx/1.23.4"},{"name":"accept-ranges","value":"bytes"},{"name":"etag","value":"\"63c15604-93ce\""},{"name":"content-length","value":"37838"},{"name":"content-type","value":"text/css"}],"_transferSize":37958},"connection":"0","serverIPAddress":"10.10.0.102","timings":{"blocked":9.078,"dns":-1,"connect":-1,"send":0.41,"wait":59.942,"receive":580.266,"ssl":-1,"_queued":8.29},"_requestTime":823783.659176},{"cache":{},"startedDateTime":"2023-02-01T15:31:55.312Z","_requestId":"3504271.11","_initialPriority":"VeryHigh","_priority":"VeryHigh","pageref":"page_1","request":{"method":"GET","url":"https://quic.totto.page/css/40k.css","queryString":[],"headersSize":-1,"bodySize":0,"cookies":[],"headers":[{"name":"sec-ch-ua","value":""},{"name":"Referer","value":"https://quic.totto.page/single.html"},{"name":"sec-ch-ua-mobile","value":"?0"},{"name":"User-Agent","value":"Mozilla/5.0 (X11; Linux x86_64) AppleWebKit/537.36 (KHTML, like Gecko) HeadlessChrome/109.0.5414.74 Safari/537.36"},{"name":"sec-ch-ua-platform","value":""}],"httpVersion":"h3"},"time":759.157,"_initiator_detail":"{\"type\":\"parser\",\"url\":\"https://quic.totto.page/single.html\",\"lineNumber\":14,\"columnNumber\":55}","_initiator_type":"parser","_initiator":"https://quic.totto.page/single.html","_initiator_line":15,"response":{"httpVersion":"h3","redirectURL":"","status":200,"statusText":"","content":{"mimeType":"text/css","size":42040},"headersSize":-1,"bodySize":42160,"cookies":[],"headers":[{"name":"date","value":"Wed, 01 Feb 2023 15:31:55 GMT"},{"name":"last-modified","value":"Fri, 13 Jan 2023 13:00:52 GMT"},{"name":"server","value":"nginx/1.23.4"},{"name":"accept-ranges","value":"bytes"},{"name":"etag","value":"\"63c15604-a438\""},{"name":"content-length","value":"42040"},{"name":"content-type","value":"text/css"}],"_transferSize":42160},"connection":"0","serverIPAddress":"10.10.0.102","timings":{"blocked":11.191,"dns":-1,"connect":-1,"send":0.418,"wait":119.674,"receive":627.874,"ssl":-1,"_queued":8.926},"_requestTime":823783.660165},{"cache":{},"startedDateTime":"2023-02-01T15:31:55.353Z","_requestId":"3504271.12","_initialPriority":"Low","_priority":"High","pageref":"page_1","request":{"method":"GET","url":"https://quic.totto.page/images/5k.jpeg","queryString":[],"headersSize":-1,"bodySize":0,"cookies":[],"headers":[{"name":"sec-ch-ua","value":""},{"name":"Referer","value":"https://quic.totto.page/single.html"},{"name":"sec-ch-ua-mobile","value":"?0"},{"name":"User-Agent","value":"Mozilla/5.0 (X11; Linux x86_64) AppleWebKit/537.36 (KHTML, like Gecko) HeadlessChrome/109.0.5414.74 Safari/537.36"},{"name":"sec-ch-ua-platform","value":""}],"httpVersion":"h3"},"time":196.856,"_initiator_detail":"{\"type\":\"parser\",\"url\":\"https://quic.totto.page/single.html\",\"lineNumber\":22,\"columnNumber\":47}","_initiator_type":"parser","_initiator":"https://quic.totto.page/single.html","_initiator_line":23,"response":{"httpVersion":"h3","redirectURL":"","status":200,"statusText":"","content":{"mimeType":"image/jpeg","size":6875},"headersSize":-1,"bodySize":6994,"cookies":[],"headers":[{"name":"date","value":"Wed, 01 Feb 2023 15:31:55 GMT"},{"name":"last-modified","value":"Fri, 13 Jan 2023 13:00:52 GMT"},{"name":"server","value":"nginx/1.23.4"},{"name":"accept-ranges","value":"bytes"},{"name":"etag","value":"\"63c15604-1adb\""},{"name":"content-length","value":"6875"},{"name":"content-type","value":"image/jpeg"}],"_transferSize":6994},"connection":"0","serverIPAddress":"10.10.0.102","timings":{"blocked":17.641,"dns":-1,"connect":-1,"send":0.214,"wait":61.163,"receive":117.838,"ssl":-1,"_queued":49.873},"_requestTime":823783.701488},{"cache":{},"startedDateTime":"2023-02-01T15:31:55.350Z","_requestId":"3504271.13","_initialPriority":"Low","_priority":"High","pageref":"page_1","request":{"method":"GET","url":"https://quic.totto.page/images/10k.jpeg","queryString":[],"headersSize":-1,"bodySize":0,"cookies":[],"headers":[{"name":"sec-ch-ua","value":""},{"name":"Referer","value":"https://quic.totto.page/single.html"},{"name":"sec-ch-ua-mobile","value":"?0"},{"name":"User-Agent","value":"Mozilla/5.0 (X11; Linux x86_64) AppleWebKit/537.36 (KHTML, like Gecko) HeadlessChrome/109.0.5414.74 Safari/537.36"},{"name":"sec-ch-ua-platform","value":""}],"httpVersion":"h3"},"time":204.758,"_initiator_detail":"{\"type\":\"parser\",\"url\":\"https://quic.totto.page/single.html\",\"lineNumber\":23,\"columnNumber\":48}","_initiator_type":"parser","_initiator":"https://quic.totto.page/single.html","_initiator_line":24,"response":{"httpVersion":"h3","redirectURL":"","status":200,"statusText":"","content":{"mimeType":"image/jpeg","size":10027},"headersSize":-1,"bodySize":10147,"cookies":[],"headers":[{"name":"date","value":"Wed, 01 Feb 2023 15:31:55 GMT"},{"name":"last-modified","value":"Fri, 13 Jan 2023 13:00:52 GMT"},{"name":"server","value":"nginx/1.23.4"},{"name":"accept-ranges","value":"bytes"},{"name":"etag","value":"\"63c15604-272b\""},{"name":"content-length","value":"10027"},{"name":"content-type","value":"image/jpeg"}],"_transferSize":10147},"connection":"0","serverIPAddress":"10.10.0.102","timings":{"blocked":14.718,"dns":-1,"connect":-1,"send":0.302,"wait":31.646,"receive":158.092,"ssl":-1,"_queued":46.375},"_requestTime":823783.698208},{"cache":{},"startedDateTime":"2023-02-01T15:31:55.351Z","_requestId":"3504271.14","_initialPriority":"Low","_priority":"High","pageref":"page_1","request":{"method":"GET","url":"https://quic.totto.page/images/15k.jpeg","queryString":[],"headersSize":-1,"bodySize":0,"cookies":[],"headers":[{"name":"sec-ch-ua","value":""},{"name":"Referer","value":"https://quic.totto.page/single.html"},{"name":"sec-ch-ua-mobile","value":"?0"},{"name":"User-Agent","value":"Mozilla/5.0 (X11; Linux x86_64) AppleWebKit/537.36 (KHTML, like Gecko) HeadlessChrome/109.0.5414.74 Safari/537.36"},{"name":"sec-ch-ua-platform","value":""}],"httpVersion":"h3"},"time":378.20599999999996,"_initiator_detail":"{\"type\":\"parser\",\"url\":\"https://quic.totto.page/single.html\",\"lineNumber\":24,\"columnNumber\":48}","_initiator_type":"parser","_initiator":"https://quic.totto.page/single.html","_initiator_line":25,"response":{"httpVersion":"h3","redirectURL":"","status":200,"statusText":"","content":{"mimeType":"image/jpeg","size":15259},"headersSize":-1,"bodySize":15379,"cookies":[],"headers":[{"name":"date","value":"Wed, 01 Feb 2023 15:31:55 GMT"},{"name":"last-modified","value":"Fri, 13 Jan 2023 13:00:52 GMT"},{"name":"server","value":"nginx/1.23.4"},{"name":"accept-ranges","value":"bytes"},{"name":"etag","value":"\"63c15604-3b9b\""},{"name":"content-length","value":"15259"},{"name":"content-type","value":"image/jpeg"}],"_transferSize":15379},"connection":"0","serverIPAddress":"10.10.0.102","timings":{"blocked":15.698,"dns":-1,"connect":-1,"send":0.216,"wait":85.832,"receive":276.46,"ssl":-1,"_queued":47.183},"_requestTime":823783.699209},{"cache":{},"startedDateTime":"2023-02-01T15:31:55.352Z","_requestId":"3504271.15","_initialPriority":"Low","_priority":"High","pageref":"page_1","request":{"method":"GET","url":"https://quic.totto.page/images/20k.jpeg","queryString":[],"headersSize":-1,"bodySize":0,"cookies":[],"headers":[{"name":"sec-ch-ua","value":""},{"name":"Referer","value":"https://quic.totto.page/single.html"},{"name":"sec-ch-ua-mobile","value":"?0"},{"name":"User-Agent","value":"Mozilla/5.0 (X11; Linux x86_64) AppleWebKit/537.36 (KHTML, like Gecko) HeadlessChrome/109.0.5414.74 Safari/537.36"},{"name":"sec-ch-ua-platform","value":""}],"httpVersion":"h3"},"time":441.47,"_initiator_detail":"{\"type\":\"parser\",\"url\":\"https://quic.totto.page/single.html\",\"lineNumber\":25,\"columnNumber\":48}","_initiator_type":"parser","_initiator":"https://quic.totto.page/single.html","_initiator_line":26,"response":{"httpVersion":"h3","redirectURL":"","status":200,"statusText":"","content":{"mimeType":"image/jpeg","size":21268},"headersSize":-1,"bodySize":21390,"cookies":[],"headers":[{"name":"date","value":"Wed, 01 Feb 2023 15:31:55 GMT"},{"name":"last-modified","value":"Fri, 13 Jan 2023 13:00:52 GMT"},{"name":"server","value":"nginx/1.23.4"},{"name":"accept-ranges","value":"bytes"},{"name":"etag","value":"\"63c15604-5314\""},{"name":"content-length","value":"21268"},{"name":"content-type","value":"image/jpeg"}],"_transferSize":21390},"connection":"0","serverIPAddress":"10.10.0.102","timings":{"blocked":16.858,"dns":-1,"connect":-1,"send":0.227,"wait":51.359,"receive":373.026,"ssl":-1,"_queued":48.296},"_requestTime":823783.700518},{"cache":{},"startedDateTime":"2023-02-01T15:31:55.351Z","_requestId":"3504271.16","_initialPriority":"Low","_priority":"High","pageref":"page_1","request":{"method":"GET","url":"https://quic.totto.page/images/25k.jpeg","queryString":[],"headersSize":-1,"bodySize":0,"cookies":[],"headers":[{"name":"sec-ch-ua","value":""},{"name":"Referer","value":"https://quic.totto.page/single.html"},{"name":"sec-ch-ua-mobile","value":"?0"},{"name":"User-Agent","value":"Mozilla/5.0 (X11; Linux x86_64) AppleWebKit/537.36 (KHTML, like Gecko) HeadlessChrome/109.0.5414.74 Safari/537.36"},{"name":"sec-ch-ua-platform","value":""}],"httpVersion":"h3"},"time":536.694,"_initiator_detail":"{\"type\":\"parser\",\"url\":\"https://quic.totto.page/single.html\",\"lineNumber\":26,\"columnNumber\":48}","_initiator_type":"parser","_initiator":"https://quic.totto.page/single.html","_initiator_line":27,"response":{"httpVersion":"h3","redirectURL":"","status":200,"statusText":"","content":{"mimeType":"image/jpeg","size":26290},"headersSize":-1,"bodySize":26412,"cookies":[],"headers":[{"name":"date","value":"Wed, 01 Feb 2023 15:31:55 GMT"},{"name":"last-modified","value":"Fri, 13 Jan 2023 13:00:52 GMT"},{"name":"server","value":"nginx/1.23.4"},{"name":"accept-ranges","value":"bytes"},{"name":"etag","value":"\"63c15604-66b2\""},{"name":"content-length","value":"26290"},{"name":"content-type","value":"image/jpeg"}],"_transferSize":26412},"connection":"0","serverIPAddress":"10.10.0.102","timings":{"blocked":15.509,"dns":-1,"connect":-1,"send":0.231,"wait":84.593,"receive":436.361,"ssl":-1,"_queued":46.607},"_requestTime":823783.699027},{"cache":{},"startedDateTime":"2023-02-01T15:31:55.351Z","_requestId":"3504271.17","_initialPriority":"Low","_priority":"High","pageref":"page_1","request":{"method":"GET","url":"https://quic.totto.page/images/30k.jpeg","queryString":[],"headersSize":-1,"bodySize":0,"cookies":[],"headers":[{"name":"sec-ch-ua","value":""},{"name":"Referer","value":"https://quic.totto.page/single.html"},{"name":"sec-ch-ua-mobile","value":"?0"},{"name":"User-Agent","value":"Mozilla/5.0 (X11; Linux x86_64) AppleWebKit/537.36 (KHTML, like Gecko) HeadlessChrome/109.0.5414.74 Safari/537.36"},{"name":"sec-ch-ua-platform","value":""}],"httpVersion":"h3"},"time":554.597,"_initiator_detail":"{\"type\":\"parser\",\"url\":\"https://quic.totto.page/single.html\",\"lineNumber\":27,\"columnNumber\":48}","_initiator_type":"parser","_initiator":"https://quic.totto.page/single.html","_initiator_line":28,"response":{"httpVersion":"h3","redirectURL":"","status":200,"statusText":"","content":{"mimeType":"image/jpeg","size":31075},"headersSize":-1,"bodySize":31197,"cookies":[],"headers":[{"name":"date","value":"Wed, 01 Feb 2023 15:31:55 GMT"},{"name":"last-modified","value":"Fri, 13 Jan 2023 13:00:52 GMT"},{"name":"server","value":"nginx/1.23.4"},{"name":"accept-ranges","value":"bytes"},{"name":"etag","value":"\"63c15604-7963\""},{"name":"content-length","value":"31075"},{"name":"content-type","value":"image/jpeg"}],"_transferSize":31197},"connection":"0","serverIPAddress":"10.10.0.102","timings":{"blocked":16.175,"dns":-1,"connect":-1,"send":0.223,"wait":36.434,"receive":501.765,"ssl":-1,"_queued":47.106},"_requestTime":823783.699766},{"cache":{},"startedDateTime":"2023-02-01T15:31:55.352Z","_requestId":"3504271.18","_initialPriority":"Low","_priority":"High","pageref":"page_1","request":{"method":"GET","url":"https://quic.totto.page/images/35k.jpeg","queryString":[],"headersSize":-1,"bodySize":0,"cookies":[],"headers":[{"name":"sec-ch-ua","value":""},{"name":"Referer","value":"https://quic.totto.page/single.html"},{"name":"sec-ch-ua-mobile","value":"?0"},{"name":"User-Agent","value":"Mozilla/5.0 (X11; Linux x86_64) AppleWebKit/537.36 (KHTML, like Gecko) HeadlessChrome/109.0.5414.74 Safari/537.36"},{"name":"sec-ch-ua-platform","value":""}],"httpVersion":"h3"},"time":671.0790000000001,"_initiator_detail":"{\"type\":\"parser\",\"url\":\"https://quic.totto.page/single.html\",\"lineNumber\":28,\"columnNumber\":48}","_initiator_type":"parser","_initiator":"https://quic.totto.page/single.html","_initiator_line":29,"response":{"httpVersion":"h3","redirectURL":"","status":200,"statusText":"","content":{"mimeType":"image/jpeg","size":36838},"headersSize":-1,"bodySize":36960,"cookies":[],"headers":[{"name":"date","value":"Wed, 01 Feb 2023 15:31:55 GMT"},{"name":"last-modified","value":"Fri, 13 Jan 2023 13:00:52 GMT"},{"name":"server","value":"nginx/1.23.4"},{"name":"accept-ranges","value":"bytes"},{"name":"etag","value":"\"63c15604-8fe6\""},{"name":"content-length","value":"36838"},{"name":"content-type","value":"image/jpeg"}],"_transferSize":36960},"connection":"0","serverIPAddress":"10.10.0.102","timings":{"blocked":16.992,"dns":-1,"connect":-1,"send":0.213,"wait":99.41,"receive":554.464,"ssl":-1,"_queued":47.83},"_requestTime":823783.700734},{"cache":{},"startedDateTime":"2023-02-01T15:31:55.350Z","_requestId":"3504271.19","_initialPriority":"Low","_priority":"High","pageref":"page_1","request":{"method":"GET","url":"https://quic.totto.page/images/40k.jpeg","queryString":[],"headersSize":-1,"bodySize":0,"cookies":[],"headers":[{"name":"sec-ch-ua","value":""},{"name":"Referer","value":"https://quic.totto.page/single.html"},{"name":"sec-ch-ua-mobile","value":"?0"},{"name":"User-Agent","value":"Mozilla/5.0 (X11; Linux x86_64) AppleWebKit/537.36 (KHTML, like Gecko) HeadlessChrome/109.0.5414.74 Safari/537.36"},{"name":"sec-ch-ua-platform","value":""}],"httpVersion":"h3"},"time":668.6659999999999,"_initiator_detail":"{\"type\":\"parser\",\"url\":\"https://quic.totto.page/single.html\",\"lineNumber\":29,\"columnNumber\":48}","_initiator_type":"parser","_initiator":"https://quic.totto.page/single.html","_initiator_line":30,"response":{"httpVersion":"h3","redirectURL":"","status":200,"statusText":"","content":{"mimeType":"image/jpeg","size":41196},"headersSize":-1,"bodySize":41318,"cookies":[],"headers":[{"name":"date","value":"Wed, 01 Feb 2023 15:31:55 GMT"},{"name":"last-modified","value":"Fri, 13 Jan 2023 13:00:52 GMT"},{"name":"server","value":"nginx/1.23.4"},{"name":"accept-ranges","value":"bytes"},{"name":"etag","value":"\"63c15604-a0ec\""},{"name":"content-length","value":"41196"},{"name":"content-type","value":"image/jpeg"}],"_transferSize":41318},"connection":"0","serverIPAddress":"10.10.0.102","timings":{"blocked":14.885,"dns":-1,"connect":-1,"send":0.235,"wait":31.607,"receive":621.939,"ssl":-1,"_queued":45.333},"_requestTime":823783.698474},{"cache":{},"startedDateTime":"2023-02-01T15:31:55.353Z","_requestId":"3504271.20","_initialPriority":"Low","_priority":"High","pageref":"page_1","request":{"method":"GET","url":"https://quic.totto.page/images/45k.jpeg","queryString":[],"headersSize":-1,"bodySize":0,"cookies":[],"headers":[{"name":"sec-ch-ua","value":""},{"name":"Referer","value":"https://quic.totto.page/single.html"},{"name":"sec-ch-ua-mobile","value":"?0"},{"name":"User-Agent","value":"Mozilla/5.0 (X11; Linux x86_64) AppleWebKit/537.36 (KHTML, like Gecko) HeadlessChrome/109.0.5414.74 Safari/537.36"},{"name":"sec-ch-ua-platform","value":""}],"httpVersion":"h3"},"time":737.135,"_initiator_detail":"{\"type\":\"parser\",\"url\":\"https://quic.totto.page/single.html\",\"lineNumber\":30,\"columnNumber\":48}","_initiator_type":"parser","_initiator":"https://quic.totto.page/single.html","_initiator_line":31,"response":{"httpVersion":"h3","redirectURL":"","status":200,"statusText":"","content":{"mimeType":"image/jpeg","size":46150},"headersSize":-1,"bodySize":46272,"cookies":[],"headers":[{"name":"date","value":"Wed, 01 Feb 2023 15:31:55 GMT"},{"name":"last-modified","value":"Fri, 13 Jan 2023 13:00:52 GMT"},{"name":"server","value":"nginx/1.23.4"},{"name":"accept-ranges","value":"bytes"},{"name":"etag","value":"\"63c15604-b446\""},{"name":"content-length","value":"46150"},{"name":"content-type","value":"image/jpeg"}],"_transferSize":46272},"connection":"0","serverIPAddress":"10.10.0.102","timings":{"blocked":17.299,"dns":-1,"connect":-1,"send":0.235,"wait":57.405,"receive":662.196,"ssl":-1,"_queued":47.797},"_requestTime":823783.701121},{"cache":{},"startedDateTime":"2023-02-01T15:31:55.351Z","_requestId":"3504271.21","_initialPriority":"Low","_priority":"High","pageref":"page_1","request":{"method":"GET","url":"https://quic.totto.page/images/50k.jpeg","queryString":[],"headersSize":-1,"bodySize":0,"cookies":[],"headers":[{"name":"sec-ch-ua","value":""},{"name":"Referer","value":"https://quic.totto.page/single.html"},{"name":"sec-ch-ua-mobile","value":"?0"},{"name":"User-Agent","value":"Mozilla/5.0 (X11; Linux x86_64) AppleWebKit/537.36 (KHTML, like Gecko) HeadlessChrome/109.0.5414.74 Safari/537.36"},{"name":"sec-ch-ua-platform","value":""}],"httpVersion":"h3"},"time":772.269,"_initiator_detail":"{\"type\":\"parser\",\"url\":\"https://quic.totto.page/single.html\",\"lineNumber\":31,\"columnNumber\":48}","_initiator_type":"parser","_initiator":"https://quic.totto.page/single.html","_initiator_line":32,"response":{"httpVersion":"h3","redirectURL":"","status":200,"statusText":"","content":{"mimeType":"image/jpeg","size":52122},"headersSize":-1,"bodySize":52244,"cookies":[],"headers":[{"name":"date","value":"Wed, 01 Feb 2023 15:31:55 GMT"},{"name":"last-modified","value":"Fri, 13 Jan 2023 13:00:52 GMT"},{"name":"server","value":"nginx/1.23.4"},{"name":"accept-ranges","value":"bytes"},{"name":"etag","value":"\"63c15604-cb9a\""},{"name":"content-length","value":"52122"},{"name":"content-type","value":"image/jpeg"}],"_transferSize":52244},"connection":"0","serverIPAddress":"10.10.0.102","timings":{"blocked":15.852,"dns":-1,"connect":-1,"send":0.221,"wait":32.325,"receive":723.871,"ssl":-1,"_queued":45.87},"_requestTime":823783.6994},{"cache":{},"startedDateTime":"2023-02-01T15:31:55.352Z","_requestId":"3504271.22","_initialPriority":"Low","_priority":"High","pageref":"page_1","request":{"method":"GET","url":"https://quic.totto.page/images/55k.jpeg","queryString":[],"headersSize":-1,"bodySize":0,"cookies":[],"headers":[{"name":"sec-ch-ua","value":""},{"name":"Referer","value":"https://quic.totto.page/single.html"},{"name":"sec-ch-ua-mobile","value":"?0"},{"name":"User-Agent","value":"Mozilla/5.0 (X11; Linux x86_64) AppleWebKit/537.36 (KHTML, like Gecko) HeadlessChrome/109.0.5414.74 Safari/537.36"},{"name":"sec-ch-ua-platform","value":""}],"httpVersion":"h3"},"time":827.754,"_initiator_detail":"{\"type\":\"parser\",\"url\":\"https://quic.totto.page/single.html\",\"lineNumber\":32,\"columnNumber\":48}","_initiator_type":"parser","_initiator":"https://quic.totto.page/single.html","_initiator_line":33,"response":{"httpVersion":"h3","redirectURL":"","status":200,"statusText":"","content":{"mimeType":"image/jpeg","size":56879},"headersSize":-1,"bodySize":57001,"cookies":[],"headers":[{"name":"date","value":"Wed, 01 Feb 2023 15:31:55 GMT"},{"name":"last-modified","value":"Fri, 13 Jan 2023 13:00:52 GMT"},{"name":"server","value":"nginx/1.23.4"},{"name":"accept-ranges","value":"bytes"},{"name":"etag","value":"\"63c15604-de2f\""},{"name":"content-length","value":"56879"},{"name":"content-type","value":"image/jpeg"}],"_transferSize":57001},"connection":"0","serverIPAddress":"10.10.0.102","timings":{"blocked":16.702,"dns":-1,"connect":-1,"send":0.223,"wait":46.886,"receive":763.943,"ssl":-1,"_queued":46.59},"_requestTime":823783.70032},{"cache":{},"startedDateTime":"2023-02-01T15:31:55.350Z","_requestId":"3504271.23","_initialPriority":"Low","_priority":"High","pageref":"page_1","request":{"method":"GET","url":"https://quic.totto.page/images/60k.jpeg","queryString":[],"headersSize":-1,"bodySize":0,"cookies":[],"headers":[{"name":"sec-ch-ua","value":""},{"name":"Referer","value":"https://quic.totto.page/single.html"},{"name":"sec-ch-ua-mobile","value":"?0"},{"name":"User-Agent","value":"Mozilla/5.0 (X11; Linux x86_64) AppleWebKit/537.36 (KHTML, like Gecko) HeadlessChrome/109.0.5414.74 Safari/537.36"},{"name":"sec-ch-ua-platform","value":""}],"httpVersion":"h3"},"time":874.979,"_initiator_detail":"{\"type\":\"parser\",\"url\":\"https://quic.totto.page/single.html\",\"lineNumber\":33,\"columnNumber\":48}","_initiator_type":"parser","_initiator":"https://quic.totto.page/single.html","_initiator_line":34,"response":{"httpVersion":"h3","redirectURL":"","status":200,"statusText":"","content":{"mimeType":"image/jpeg","size":62344},"headersSize":-1,"bodySize":62466,"cookies":[],"headers":[{"name":"date","value":"Wed, 01 Feb 2023 15:31:55 GMT"},{"name":"last-modified","value":"Fri, 13 Jan 2023 13:00:52 GMT"},{"name":"server","value":"nginx/1.23.4"},{"name":"accept-ranges","value":"bytes"},{"name":"etag","value":"\"63c15604-f388\""},{"name":"content-length","value":"62344"},{"name":"content-type","value":"image/jpeg"}],"_transferSize":62466},"connection":"0","serverIPAddress":"10.10.0.102","timings":{"blocked":15.245,"dns":-1,"connect":-1,"send":0.309,"wait":81.001,"receive":778.424,"ssl":-1,"_queued":44.925},"_requestTime":823783.698843},{"cache":{},"startedDateTime":"2023-02-01T15:31:55.351Z","_requestId":"3504271.24","_initialPriority":"Low","_priority":"High","pageref":"page_1","request":{"method":"GET","url":"https://quic.totto.page/images/65k.jpeg","queryString":[],"headersSize":-1,"bodySize":0,"cookies":[],"headers":[{"name":"sec-ch-ua","value":""},{"name":"Referer","value":"https://quic.totto.page/single.html"},{"name":"sec-ch-ua-mobile","value":"?0"},{"name":"User-Agent","value":"Mozilla/5.0 (X11; Linux x86_64) AppleWebKit/537.36 (KHTML, like Gecko) HeadlessChrome/109.0.5414.74 Safari/537.36"},{"name":"sec-ch-ua-platform","value":""}],"httpVersion":"h3"},"time":890.95,"_initiator_detail":"{\"type\":\"parser\",\"url\":\"https://quic.totto.page/single.html\",\"lineNumber\":34,\"columnNumber\":48}","_initiator_type":"parser","_initiator":"https://quic.totto.page/single.html","_initiator_line":35,"response":{"httpVersion":"h3","redirectURL":"","status":200,"statusText":"","content":{"mimeType":"image/jpeg","size":67587},"headersSize":-1,"bodySize":67710,"cookies":[],"headers":[{"name":"date","value":"Wed, 01 Feb 2023 15:31:55 GMT"},{"name":"last-modified","value":"Fri, 13 Jan 2023 13:00:52 GMT"},{"name":"server","value":"nginx/1.23.4"},{"name":"accept-ranges","value":"bytes"},{"name":"etag","value":"\"63c15604-10803\""},{"name":"content-length","value":"67587"},{"name":"content-type","value":"image/jpeg"}],"_transferSize":67710},"connection":"0","serverIPAddress":"10.10.0.102","timings":{"blocked":16.018,"dns":-1,"connect":-1,"send":0.219,"wait":32.275,"receive":842.438,"ssl":-1,"_queued":45.456},"_requestTime":823783.699578},{"cache":{},"startedDateTime":"2023-02-01T15:31:55.353Z","_requestId":"3504271.25","_initialPriority":"Low","_priority":"High","pageref":"page_1","request":{"method":"GET","url":"https://quic.totto.page/images/70k.jpeg","queryString":[],"headersSize":-1,"bodySize":0,"cookies":[],"headers":[{"name":"sec-ch-ua","value":""},{"name":"Referer","value":"https://quic.totto.page/single.html"},{"name":"sec-ch-ua-mobile","value":"?0"},{"name":"User-Agent","value":"Mozilla/5.0 (X11; Linux x86_64) AppleWebKit/537.36 (KHTML, like Gecko) HeadlessChrome/109.0.5414.74 Safari/537.36"},{"name":"sec-ch-ua-platform","value":""}],"httpVersion":"h3"},"time":916.444,"_initiator_detail":"{\"type\":\"parser\",\"url\":\"https://quic.totto.page/single.html\",\"lineNumber\":35,\"columnNumber\":48}","_initiator_type":"parser","_initiator":"https://quic.totto.page/single.html","_initiator_line":36,"response":{"httpVersion":"h3","redirectURL":"","status":200,"statusText":"","content":{"mimeType":"image/jpeg","size":70979},"headersSize":-1,"bodySize":71102,"cookies":[],"headers":[{"name":"date","value":"Wed, 01 Feb 2023 15:31:55 GMT"},{"name":"last-modified","value":"Fri, 13 Jan 2023 13:00:52 GMT"},{"name":"server","value":"nginx/1.23.4"},{"name":"accept-ranges","value":"bytes"},{"name":"etag","value":"\"63c15604-11543\""},{"name":"content-length","value":"70979"},{"name":"content-type","value":"image/jpeg"}],"_transferSize":71102},"connection":"0","serverIPAddress":"10.10.0.102","timings":{"blocked":17.792,"dns":-1,"connect":-1,"send":0.225,"wait":61.148,"receive":837.279,"ssl":-1,"_queued":47.367},"_requestTime":823783.701673},{"cache":{},"startedDateTime":"2023-02-01T15:31:55.352Z","_requestId":"3504271.26","_initialPriority":"Low","_priority":"High","pageref":"page_1","request":{"method":"GET","url":"https://quic.totto.page/images/75k.jpeg","queryString":[],"headersSize":-1,"bodySize":0,"cookies":[],"headers":[{"name":"sec-ch-ua","value":""},{"name":"Referer","value":"https://quic.totto.page/single.html"},{"name":"sec-ch-ua-mobile","value":"?0"},{"name":"User-Agent","value":"Mozilla/5.0 (X11; Linux x86_64) AppleWebKit/537.36 (KHTML, like Gecko) HeadlessChrome/109.0.5414.74 Safari/537.36"},{"name":"sec-ch-ua-platform","value":""}],"httpVersion":"h3"},"time":938.124,"_initiator_detail":"{\"type\":\"parser\",\"url\":\"https://quic.totto.page/single.html\",\"lineNumber\":36,\"columnNumber\":48}","_initiator_type":"parser","_initiator":"https://quic.totto.page/single.html","_initiator_line":37,"response":{"httpVersion":"h3","redirectURL":"","status":200,"statusText":"","content":{"mimeType":"image/jpeg","size":77591},"headersSize":-1,"bodySize":77714,"cookies":[],"headers":[{"name":"date","value":"Wed, 01 Feb 2023 15:31:55 GMT"},{"name":"last-modified","value":"Fri, 13 Jan 2023 13:00:52 GMT"},{"name":"server","value":"nginx/1.23.4"},{"name":"accept-ranges","value":"bytes"},{"name":"etag","value":"\"63c15604-12f17\""},{"name":"content-length","value":"77591"},{"name":"content-type","value":"image/jpeg"}],"_transferSize":77714},"connection":"0","serverIPAddress":"10.10.0.102","timings":{"blocked":16.351,"dns":-1,"connect":-1,"send":0.223,"wait":36.465,"receive":885.085,"ssl":-1,"_queued":45.437},"_requestTime":823783.699942},{"cache":{},"startedDateTime":"2023-02-01T15:31:55.350Z","_requestId":"3504271.27","_initialPriority":"Low","_priority":"High","pageref":"page_1","request":{"method":"GET","url":"https://quic.totto.page/images/80k.jpeg","queryString":[],"headersSize":-1,"bodySize":0,"cookies":[],"headers":[{"name":"sec-ch-ua","value":""},{"name":"Referer","value":"https://quic.totto.page/single.html"},{"name":"sec-ch-ua-mobile","value":"?0"},{"name":"User-Agent","value":"Mozilla/5.0 (X11; Linux x86_64) AppleWebKit/537.36 (KHTML, like Gecko) HeadlessChrome/109.0.5414.74 Safari/537.36"},{"name":"sec-ch-ua-platform","value":""}],"httpVersion":"h3"},"time":960.473,"_initiator_detail":"{\"type\":\"parser\",\"url\":\"https://quic.totto.page/single.html\",\"lineNumber\":37,\"columnNumber\":48}","_initiator_type":"parser","_initiator":"https://quic.totto.page/single.html","_initiator_line":38,"response":{"httpVersion":"h3","redirectURL":"","status":200,"statusText":"","content":{"mimeType":"image/jpeg","size":82480},"headersSize":-1,"bodySize":82603,"cookies":[],"headers":[{"name":"date","value":"Wed, 01 Feb 2023 15:31:55 GMT"},{"name":"last-modified","value":"Fri, 13 Jan 2023 13:00:52 GMT"},{"name":"server","value":"nginx/1.23.4"},{"name":"accept-ranges","value":"bytes"},{"name":"etag","value":"\"63c15604-14230\""},{"name":"content-length","value":"82480"},{"name":"content-type","value":"image/jpeg"}],"_transferSize":82603},"connection":"0","serverIPAddress":"10.10.0.102","timings":{"blocked":15.062,"dns":-1,"connect":-1,"send":0.23,"wait":31.479,"receive":913.702,"ssl":-1,"_queued":43.96},"_requestTime":823783.698661},{"cache":{},"startedDateTime":"2023-02-01T15:31:55.353Z","_requestId":"3504271.28","_initialPriority":"Low","_priority":"High","pageref":"page_1","request":{"method":"GET","url":"https://quic.totto.page/images/85k.jpeg","queryString":[],"headersSize":-1,"bodySize":0,"cookies":[],"headers":[{"name":"sec-ch-ua","value":""},{"name":"Referer","value":"https://quic.totto.page/single.html"},{"name":"sec-ch-ua-mobile","value":"?0"},{"name":"User-Agent","value":"Mozilla/5.0 (X11; Linux x86_64) AppleWebKit/537.36 (KHTML, like Gecko) HeadlessChrome/109.0.5414.74 Safari/537.36"},{"name":"sec-ch-ua-platform","value":""}],"httpVersion":"h3"},"time":979.164,"_initiator_detail":"{\"type\":\"parser\",\"url\":\"https://quic.totto.page/single.html\",\"lineNumber\":38,\"columnNumber\":48}","_initiator_type":"parser","_initiator":"https://quic.totto.page/single.html","_initiator_line":39,"response":{"httpVersion":"h3","redirectURL":"","status":200,"statusText":"","content":{"mimeType":"image/jpeg","size":86298},"headersSize":-1,"bodySize":86421,"cookies":[],"headers":[{"name":"date","value":"Wed, 01 Feb 2023 15:31:55 GMT"},{"name":"last-modified","value":"Fri, 13 Jan 2023 13:00:52 GMT"},{"name":"server","value":"nginx/1.23.4"},{"name":"accept-ranges","value":"bytes"},{"name":"etag","value":"\"63c15604-1511a\""},{"name":"content-length","value":"86298"},{"name":"content-type","value":"image/jpeg"}],"_transferSize":86421},"connection":"0","serverIPAddress":"10.10.0.102","timings":{"blocked":17.967,"dns":-1,"connect":-1,"send":0.219,"wait":67.526,"receive":893.452,"ssl":-1,"_queued":46.962},"_requestTime":823783.701857},{"cache":{},"startedDateTime":"2023-02-01T15:31:55.353Z","_requestId":"3504271.29","_initialPriority":"Low","_priority":"High","pageref":"page_1","request":{"method":"GET","url":"https://quic.totto.page/images/90k.jpeg","queryString":[],"headersSize":-1,"bodySize":0,"cookies":[],"headers":[{"name":"sec-ch-ua","value":""},{"name":"Referer","value":"https://quic.totto.page/single.html"},{"name":"sec-ch-ua-mobile","value":"?0"},{"name":"User-Agent","value":"Mozilla/5.0 (X11; Linux x86_64) AppleWebKit/537.36 (KHTML, like Gecko) HeadlessChrome/109.0.5414.74 Safari/537.36"},{"name":"sec-ch-ua-platform","value":""}],"httpVersion":"h3"},"time":1000.333,"_initiator_detail":"{\"type\":\"parser\",\"url\":\"https://quic.totto.page/single.html\",\"lineNumber\":39,\"columnNumber\":48}","_initiator_type":"parser","_initiator":"https://quic.totto.page/single.html","_initiator_line":40,"response":{"httpVersion":"h3","redirectURL":"","status":200,"statusText":"","content":{"mimeType":"image/jpeg","size":92696},"headersSize":-1,"bodySize":92819,"cookies":[],"headers":[{"name":"date","value":"Wed, 01 Feb 2023 15:31:55 GMT"},{"name":"last-modified","value":"Fri, 13 Jan 2023 13:00:52 GMT"},{"name":"server","value":"nginx/1.23.4"},{"name":"accept-ranges","value":"bytes"},{"name":"etag","value":"\"63c15604-16a18\""},{"name":"content-length","value":"92696"},{"name":"content-type","value":"image/jpeg"}],"_transferSize":92819},"connection":"0","serverIPAddress":"10.10.0.102","timings":{"blocked":17.475,"dns":-1,"connect":-1,"send":0.211,"wait":90.825,"receive":891.822,"ssl":-1,"_queued":46.228},"_requestTime":823783.70131},{"cache":{},"startedDateTime":"2023-02-01T15:31:55.352Z","_requestId":"3504271.30","_initialPriority":"Low","_priority":"High","pageref":"page_1","request":{"method":"GET","url":"https://quic.totto.page/images/95k.jpeg","queryString":[],"headersSize":-1,"bodySize":0,"cookies":[],"headers":[{"name":"sec-ch-ua","value":""},{"name":"Referer","value":"https://quic.totto.page/single.html"},{"name":"sec-ch-ua-mobile","value":"?0"},{"name":"User-Agent","value":"Mozilla/5.0 (X11; Linux x86_64) AppleWebKit/537.36 (KHTML, like Gecko) HeadlessChrome/109.0.5414.74 Safari/537.36"},{"name":"sec-ch-ua-platform","value":""}],"httpVersion":"h3"},"time":993.309,"_initiator_detail":"{\"type\":\"parser\",\"url\":\"https://quic.totto.page/single.html\",\"lineNumber\":40,\"columnNumber\":48}","_initiator_type":"parser","_initiator":"https://quic.totto.page/single.html","_initiator_line":41,"response":{"httpVersion":"h3","redirectURL":"","status":200,"statusText":"","content":{"mimeType":"image/jpeg","size":92696},"headersSize":-1,"bodySize":92819,"cookies":[],"headers":[{"name":"date","value":"Wed, 01 Feb 2023 15:31:55 GMT"},{"name":"last-modified","value":"Fri, 13 Jan 2023 13:00:52 GMT"},{"name":"server","value":"nginx/1.23.4"},{"name":"accept-ranges","value":"bytes"},{"name":"etag","value":"\"63c15604-16a18\""},{"name":"content-length","value":"92696"},{"name":"content-type","value":"image/jpeg"}],"_transferSize":92819},"connection":"0","serverIPAddress":"10.10.0.102","timings":{"blocked":16.537,"dns":-1,"connect":-1,"send":0.213,"wait":42.818,"receive":933.741,"ssl":-1,"_queued":44.838},"_requestTime":823783.700128},{"cache":{},"startedDateTime":"2023-02-01T15:31:55.353Z","_requestId":"3504271.31","_initialPriority":"Low","_priority":"High","pageref":"page_1","request":{"method":"GET","url":"https://quic.totto.page/images/100k.jpeg","queryString":[],"headersSize":-1,"bodySize":0,"cookies":[],"headers":[{"name":"sec-ch-ua","value":""},{"name":"Referer","value":"https://quic.totto.page/single.html"},{"name":"sec-ch-ua-mobile","value":"?0"},{"name":"User-Agent","value":"Mozilla/5.0 (X11; Linux x86_64) AppleWebKit/537.36 (KHTML, like Gecko) HeadlessChrome/109.0.5414.74 Safari/537.36"},{"name":"sec-ch-ua-platform","value":""}],"httpVersion":"h3"},"time":1018.298,"_initiator_detail":"{\"type\":\"parser\",\"url\":\"https://quic.totto.page/single.html\",\"lineNumber\":41,\"columnNumber\":49}","_initiator_type":"parser","_initiator":"https://quic.totto.page/single.html","_initiator_line":42,"response":{"httpVersion":"h3","redirectURL":"","status":200,"statusText":"","content":{"mimeType":"image/jpeg","size":102868},"headersSize":-1,"bodySize":102992,"cookies":[],"headers":[{"name":"date","value":"Wed, 01 Feb 2023 15:31:55 GMT"},{"name":"last-modified","value":"Fri, 13 Jan 2023 13:00:52 GMT"},{"name":"server","value":"nginx/1.23.4"},{"name":"accept-ranges","value":"bytes"},{"name":"etag","value":"\"63c15604-191d4\""},{"name":"content-length","value":"102868"},{"name":"content-type","value":"image/jpeg"}],"_transferSize":102992},"connection":"0","serverIPAddress":"10.10.0.102","timings":{"blocked":17.152,"dns":-1,"connect":-1,"send":0.225,"wait":50.971,"receive":949.95,"ssl":-1,"_queued":45.44},"_requestTime":823783.70092},{"cache":{},"startedDateTime":"2023-02-01T15:31:56.290Z","_requestId":"3504271.32","_initialPriority":"Low","_priority":"Low","pageref":"page_1","request":{"method":"GET","url":"https://quic.totto.page/js/2k.js","queryString":[],"headersSize":-1,"bodySize":0,"cookies":[],"headers":[{"name":"sec-ch-ua","value":""},{"name":"Referer","value":"https://quic.totto.page/single.html"},{"name":"sec-ch-ua-mobile","value":"?0"},{"name":"User-Agent","value":"Mozilla/5.0 (X11; Linux x86_64) AppleWebKit/537.36 (KHTML, like Gecko) HeadlessChrome/109.0.5414.74 Safari/537.36"},{"name":"sec-ch-ua-platform","value":""}],"httpVersion":"h3"},"time":31.849999999999998,"_initiator_detail":"{\"type\":\"parser\",\"url\":\"https://quic.totto.page/single.html\",\"lineNumber\":42,\"columnNumber\":32}","_initiator_type":"parser","_initiator":"https://quic.totto.page/single.html","_initiator_line":43,"response":{"httpVersion":"h3","redirectURL":"","status":200,"statusText":"","content":{"mimeType":"application/javascript","size":2125},"headersSize":-1,"bodySize":2252,"cookies":[],"headers":[{"name":"date","value":"Wed, 01 Feb 2023 15:31:56 GMT"},{"name":"last-modified","value":"Fri, 13 Jan 2023 13:00:52 GMT"},{"name":"server","value":"nginx/1.23.4"},{"name":"accept-ranges","value":"bytes"},{"name":"etag","value":"\"63c15604-84d\""},{"name":"content-length","value":"2125"},{"name":"content-type","value":"application/javascript"}],"_transferSize":2252},"connection":"0","serverIPAddress":"10.10.0.102","timings":{"blocked":0.748,"dns":-1,"connect":-1,"send":0.376,"wait":24.612,"receive":6.114,"ssl":-1,"_queued":982.888},"_requestTime":823784.638581},{"cache":{},"startedDateTime":"2023-02-01T15:31:56.311Z","_requestId":"3504271.33","_initialPriority":"Low","_priority":"Low","pageref":"page_1","request":{"method":"GET","url":"https://quic.totto.page/js/4k.js","queryString":[],"headersSize":-1,"bodySize":0,"cookies":[],"headers":[{"name":"sec-ch-ua","value":""},{"name":"Referer","value":"https://quic.totto.page/single.html"},{"name":"sec-ch-ua-mobile","value":"?0"},{"name":"User-Agent","value":"Mozilla/5.0 (X11; Linux x86_64) AppleWebKit/537.36 (KHTML, like Gecko) HeadlessChrome/109.0.5414.74 Safari/537.36"},{"name":"sec-ch-ua-platform","value":""}],"httpVersion":"h3"},"time":35.705,"_initiator_detail":"{\"type\":\"parser\",\"url\":\"https://quic.totto.page/single.html\",\"lineNumber\":43,\"columnNumber\":32}","_initiator_type":"parser","_initiator":"https://quic.totto.page/single.html","_initiator_line":44,"response":{"httpVersion":"h3","redirectURL":"","status":200,"statusText":"","content":{"mimeType":"application/javascript","size":4227},"headersSize":-1,"bodySize":4354,"cookies":[],"headers":[{"name":"date","value":"Wed, 01 Feb 2023 15:31:56 GMT"},{"name":"last-modified","value":"Fri, 13 Jan 2023 13:00:52 GMT"},{"name":"server","value":"nginx/1.23.4"},{"name":"accept-ranges","value":"bytes"},{"name":"etag","value":"\"63c15604-1083\""},{"name":"content-length","value":"4227"},{"name":"content-type","value":"application/javascript"}],"_transferSize":4354},"connection":"0","serverIPAddress":"10.10.0.102","timings":{"blocked":0.796,"dns":-1,"connect":-1,"send":0.385,"wait":23.964,"receive":10.56,"ssl":-1,"_queued":1003.67},"_requestTime":823784.659606},{"cache":{},"startedDateTime":"2023-02-01T15:31:56.322Z","_requestId":"3504271.34","_initialPriority":"Low","_priority":"Low","pageref":"page_1","request":{"method":"GET","url":"https://quic.totto.page/js/6k.js","queryString":[],"headersSize":-1,"bodySize":0,"cookies":[],"headers":[{"name":"sec-ch-ua","value":""},{"name":"Referer","value":"https://quic.totto.page/single.html"},{"name":"sec-ch-ua-mobile","value":"?0"},{"name":"User-Agent","value":"Mozilla/5.0 (X11; Linux x86_64) AppleWebKit/537.36 (KHTML, like Gecko) HeadlessChrome/109.0.5414.74 Safari/537.36"},{"name":"sec-ch-ua-platform","value":""}],"httpVersion":"h3"},"time":40.196,"_initiator_detail":"{\"type\":\"parser\",\"url\":\"https://quic.totto.page/single.html\",\"lineNumber\":44,\"columnNumber\":32}","_initiator_type":"parser","_initiator":"https://quic.totto.page/single.html","_initiator_line":45,"response":{"httpVersion":"h3","redirectURL":"","status":200,"statusText":"","content":{"mimeType":"application/javascript","size":6327},"headersSize":-1,"bodySize":6454,"cookies":[],"headers":[{"name":"date","value":"Wed, 01 Feb 2023 15:31:56 GMT"},{"name":"last-modified","value":"Fri, 13 Jan 2023 13:00:52 GMT"},{"name":"server","value":"nginx/1.23.4"},{"name":"accept-ranges","value":"bytes"},{"name":"etag","value":"\"63c15604-18b7\""},{"name":"content-length","value":"6327"},{"name":"content-type","value":"application/javascript"}],"_transferSize":6454},"connection":"0","serverIPAddress":"10.10.0.102","timings":{"blocked":0.619,"dns":-1,"connect":-1,"send":0.38,"wait":26.531,"receive":12.666,"ssl":-1,"_queued":1014.685},"_requestTime":823784.67086},{"cache":{},"startedDateTime":"2023-02-01T15:31:56.333Z","_requestId":"3504271.35","_initialPriority":"Low","_priority":"Low","pageref":"page_1","request":{"method":"GET","url":"https://quic.totto.page/js/8k.js","queryString":[],"headersSize":-1,"bodySize":0,"cookies":[],"headers":[{"name":"sec-ch-ua","value":""},{"name":"Referer","value":"https://quic.totto.page/single.html"},{"name":"sec-ch-ua-mobile","value":"?0"},{"name":"User-Agent","value":"Mozilla/5.0 (X11; Linux x86_64) AppleWebKit/537.36 (KHTML, like Gecko) HeadlessChrome/109.0.5414.74 Safari/537.36"},{"name":"sec-ch-ua-platform","value":""}],"httpVersion":"h3"},"time":38.752,"_initiator_detail":"{\"type\":\"parser\",\"url\":\"https://quic.totto.page/single.html\",\"lineNumber\":45,\"columnNumber\":32}","_initiator_type":"parser","_initiator":"https://quic.totto.page/single.html","_initiator_line":46,"response":{"httpVersion":"h3","redirectURL":"","status":200,"statusText":"","content":{"mimeType":"application/javascript","size":8429},"headersSize":-1,"bodySize":8556,"cookies":[],"headers":[{"name":"date","value":"Wed, 01 Feb 2023 15:31:56 GMT"},{"name":"last-modified","value":"Fri, 13 Jan 2023 13:00:52 GMT"},{"name":"server","value":"nginx/1.23.4"},{"name":"accept-ranges","value":"bytes"},{"name":"etag","value":"\"63c15604-20ed\""},{"name":"content-length","value":"8429"},{"name":"content-type","value":"application/javascript"}],"_transferSize":8556},"connection":"0","serverIPAddress":"10.10.0.102","timings":{"blocked":0.797,"dns":-1,"connect":-1,"send":0.355,"wait":23.623,"receive":13.977,"ssl":-1,"_queued":1025.084},"_requestTime":823784.681464},{"cache":{},"startedDateTime":"2023-02-01T15:31:56.345Z","_requestId":"3504271.36","_initialPriority":"Low","_priority":"Low","pageref":"page_1","request":{"method":"GET","url":"https://quic.totto.page/js/10k.js","queryString":[],"headersSize":-1,"bodySize":0,"cookies":[],"headers":[{"name":"sec-ch-ua","value":""},{"name":"Referer","value":"https://quic.totto.page/single.html"},{"name":"sec-ch-ua-mobile","value":"?0"},{"name":"User-Agent","value":"Mozilla/5.0 (X11; Linux x86_64) AppleWebKit/537.36 (KHTML, like Gecko) HeadlessChrome/109.0.5414.74 Safari/537.36"},{"name":"sec-ch-ua-platform","value":""}],"httpVersion":"h3"},"time":44.701,"_initiator_detail":"{\"type\":\"parser\",\"url\":\"https://quic.totto.page/single.html\",\"lineNumber\":46,\"columnNumber\":33}","_initiator_type":"parser","_initiator":"https://quic.totto.page/single.html","_initiator_line":47,"response":{"httpVersion":"h3","redirectURL":"","status":200,"statusText":"","content":{"mimeType":"application/javascript","size":10529},"headersSize":-1,"bodySize":10657,"cookies":[],"headers":[{"name":"date","value":"Wed, 01 Feb 2023 15:31:56 GMT"},{"name":"last-modified","value":"Fri, 13 Jan 2023 13:00:52 GMT"},{"name":"server","value":"nginx/1.23.4"},{"name":"accept-ranges","value":"bytes"},{"name":"etag","value":"\"63c15604-2921\""},{"name":"content-length","value":"10529"},{"name":"content-type","value":"application/javascript"}],"_transferSize":10657},"connection":"0","serverIPAddress":"10.10.0.102","timings":{"blocked":0.837,"dns":-1,"connect":-1,"send":0.376,"wait":21.75,"receive":21.738,"ssl":-1,"_queued":1037.299},"_requestTime":823784.693863},{"cache":{},"startedDateTime":"2023-02-01T15:31:56.347Z","_requestId":"3504271.37","_initialPriority":"Low","_priority":"Low","pageref":"page_1","request":{"method":"GET","url":"https://quic.totto.page/js/12k.js","queryString":[],"headersSize":-1,"bodySize":0,"cookies":[],"headers":[{"name":"sec-ch-ua","value":""},{"name":"Referer","value":"https://quic.totto.page/single.html"},{"name":"sec-ch-ua-mobile","value":"?0"},{"name":"User-Agent","value":"Mozilla/5.0 (X11; Linux x86_64) AppleWebKit/537.36 (KHTML, like Gecko) HeadlessChrome/109.0.5414.74 Safari/537.36"},{"name":"sec-ch-ua-platform","value":""}],"httpVersion":"h3"},"time":57.153000000000006,"_initiator_detail":"{\"type\":\"parser\",\"url\":\"https://quic.totto.page/single.html\",\"lineNumber\":47,\"columnNumber\":33}","_initiator_type":"parser","_initiator":"https://quic.totto.page/single.html","_initiator_line":48,"response":{"httpVersion":"h3","redirectURL":"","status":200,"statusText":"","content":{"mimeType":"application/javascript","size":12631},"headersSize":-1,"bodySize":12759,"cookies":[],"headers":[{"name":"date","value":"Wed, 01 Feb 2023 15:31:56 GMT"},{"name":"last-modified","value":"Fri, 13 Jan 2023 13:00:52 GMT"},{"name":"server","value":"nginx/1.23.4"},{"name":"accept-ranges","value":"bytes"},{"name":"etag","value":"\"63c15604-3157\""},{"name":"content-length","value":"12631"},{"name":"content-type","value":"application/javascript"}],"_transferSize":12759},"connection":"0","serverIPAddress":"10.10.0.102","timings":{"blocked":2.099,"dns":-1,"connect":-1,"send":0.346,"wait":23.724,"receive":30.984,"ssl":-1,"_queued":1038.978},"_requestTime":823784.695798},{"cache":{},"startedDateTime":"2023-02-01T15:31:56.354Z","_requestId":"3504271.38","_initialPriority":"Low","_priority":"Low","pageref":"page_1","request":{"method":"GET","url":"https://quic.totto.page/js/14k.js","queryString":[],"headersSize":-1,"bodySize":0,"cookies":[],"headers":[{"name":"sec-ch-ua","value":""},{"name":"Referer","value":"https://quic.totto.page/single.html"},{"name":"sec-ch-ua-mobile","value":"?0"},{"name":"User-Agent","value":"Mozilla/5.0 (X11; Linux x86_64) AppleWebKit/537.36 (KHTML, like Gecko) HeadlessChrome/109.0.5414.74 Safari/537.36"},{"name":"sec-ch-ua-platform","value":""}],"httpVersion":"h3"},"time":72.48,"_initiator_detail":"{\"type\":\"parser\",\"url\":\"https://quic.totto.page/single.html\",\"lineNumber\":48,\"columnNumber\":33}","_initiator_type":"parser","_initiator":"https://quic.totto.page/single.html","_initiator_line":49,"response":{"httpVersion":"h3","redirectURL":"","status":200,"statusText":"","content":{"mimeType":"application/javascript","size":14733},"headersSize":-1,"bodySize":14861,"cookies":[],"headers":[{"name":"date","value":"Wed, 01 Feb 2023 15:31:56 GMT"},{"name":"last-modified","value":"Fri, 13 Jan 2023 13:00:52 GMT"},{"name":"server","value":"nginx/1.23.4"},{"name":"accept-ranges","value":"bytes"},{"name":"etag","value":"\"63c15604-398d\""},{"name":"content-length","value":"14733"},{"name":"content-type","value":"application/javascript"}],"_transferSize":14861},"connection":"0","serverIPAddress":"10.10.0.102","timings":{"blocked":1.23,"dns":-1,"connect":-1,"send":0.348,"wait":25.565,"receive":45.337,"ssl":-1,"_queued":1045.014},"_requestTime":823784.702052},{"cache":{},"startedDateTime":"2023-02-01T15:31:56.363Z","_requestId":"3504271.39","_initialPriority":"Low","_priority":"Low","pageref":"page_1","request":{"method":"GET","url":"https://quic.totto.page/js/16k.js","queryString":[],"headersSize":-1,"bodySize":0,"cookies":[],"headers":[{"name":"sec-ch-ua","value":""},{"name":"Referer","value":"https://quic.totto.page/single.html"},{"name":"sec-ch-ua-mobile","value":"?0"},{"name":"User-Agent","value":"Mozilla/5.0 (X11; Linux x86_64) AppleWebKit/537.36 (KHTML, like Gecko) HeadlessChrome/109.0.5414.74 Safari/537.36"},{"name":"sec-ch-ua-platform","value":""}],"httpVersion":"h3"},"time":83.17599999999999,"_initiator_detail":"{\"type\":\"parser\",\"url\":\"https://quic.totto.page/single.html\",\"lineNumber\":49,\"columnNumber\":33}","_initiator_type":"parser","_initiator":"https://quic.totto.page/single.html","_initiator_line":50,"response":{"httpVersion":"h3","redirectURL":"","status":200,"statusText":"","content":{"mimeType":"application/javascript","size":16833},"headersSize":-1,"bodySize":16963,"cookies":[],"headers":[{"name":"date","value":"Wed, 01 Feb 2023 15:31:56 GMT"},{"name":"last-modified","value":"Fri, 13 Jan 2023 13:00:52 GMT"},{"name":"server","value":"nginx/1.23.4"},{"name":"accept-ranges","value":"bytes"},{"name":"etag","value":"\"63c15604-41c1\""},{"name":"content-length","value":"16833"},{"name":"content-type","value":"application/javascript"}],"_transferSize":16963},"connection":"0","serverIPAddress":"10.10.0.102","timings":{"blocked":0.642,"dns":-1,"connect":-1,"send":0.343,"wait":22.769,"receive":59.422,"ssl":-1,"_queued":1054.198},"_requestTime":823784.711438},{"cache":{},"startedDateTime":"2023-02-01T15:31:56.371Z","_requestId":"3504271.40","_initialPriority":"Low","_priority":"Low","pageref":"page_1","request":{"method":"GET","url":"https://quic.totto.page/js/18k.js","queryString":[],"headersSize":-1,"bodySize":0,"cookies":[],"headers":[{"name":"sec-ch-ua","value":""},{"name":"Referer","value":"https://quic.totto.page/single.html"},{"name":"sec-ch-ua-mobile","value":"?0"},{"name":"User-Agent","value":"Mozilla/5.0 (X11; Linux x86_64) AppleWebKit/537.36 (KHTML, like Gecko) HeadlessChrome/109.0.5414.74 Safari/537.36"},{"name":"sec-ch-ua-platform","value":""}],"httpVersion":"h3"},"time":91.423,"_initiator_detail":"{\"type\":\"parser\",\"url\":\"https://quic.totto.page/single.html\",\"lineNumber\":50,\"columnNumber\":33}","_initiator_type":"parser","_initiator":"https://quic.totto.page/single.html","_initiator_line":51,"response":{"httpVersion":"h3","redirectURL":"","status":200,"statusText":"","content":{"mimeType":"application/javascript","size":18935},"headersSize":-1,"bodySize":19065,"cookies":[],"headers":[{"name":"date","value":"Wed, 01 Feb 2023 15:31:56 GMT"},{"name":"last-modified","value":"Fri, 13 Jan 2023 13:00:52 GMT"},{"name":"server","value":"nginx/1.23.4"},{"name":"accept-ranges","value":"bytes"},{"name":"etag","value":"\"63c15604-49f7\""},{"name":"content-length","value":"18935"},{"name":"content-type","value":"application/javascript"}],"_transferSize":19065},"connection":"0","serverIPAddress":"10.10.0.102","timings":{"blocked":1.725,"dns":-1,"connect":-1,"send":0.367,"wait":23.176,"receive":66.155,"ssl":-1,"_queued":1062.316},"_requestTime":823784.719744},{"cache":{},"startedDateTime":"2023-02-01T15:31:56.373Z","_requestId":"3504271.41","_initialPriority":"Low","_priority":"Low","pageref":"page_1","request":{"method":"GET","url":"https://quic.totto.page/js/20k.js","queryString":[],"headersSize":-1,"bodySize":0,"cookies":[],"headers":[{"name":"sec-ch-ua","value":""},{"name":"Referer","value":"https://quic.totto.page/single.html"},{"name":"sec-ch-ua-mobile","value":"?0"},{"name":"User-Agent","value":"Mozilla/5.0 (X11; Linux x86_64) AppleWebKit/537.36 (KHTML, like Gecko) HeadlessChrome/109.0.5414.74 Safari/537.36"},{"name":"sec-ch-ua-platform","value":""}],"httpVersion":"h3"},"time":102.446,"_initiator_detail":"{\"type\":\"parser\",\"url\":\"https://quic.totto.page/single.html\",\"lineNumber\":51,\"columnNumber\":33}","_initiator_type":"parser","_initiator":"https://quic.totto.page/single.html","_initiator_line":52,"response":{"httpVersion":"h3","redirectURL":"","status":200,"statusText":"","content":{"mimeType":"application/javascript","size":21035},"headersSize":-1,"bodySize":21165,"cookies":[],"headers":[{"name":"date","value":"Wed, 01 Feb 2023 15:31:56 GMT"},{"name":"last-modified","value":"Fri, 13 Jan 2023 13:00:52 GMT"},{"name":"server","value":"nginx/1.23.4"},{"name":"accept-ranges","value":"bytes"},{"name":"etag","value":"\"63c15604-522b\""},{"name":"content-length","value":"21035"},{"name":"content-type","value":"application/javascript"}],"_transferSize":21165},"connection":"0","serverIPAddress":"10.10.0.102","timings":{"blocked":2.047,"dns":-1,"connect":-1,"send":0.341,"wait":22.365,"receive":77.693,"ssl":-1,"_queued":1063.421},"_requestTime":823784.721049},{"cache":{},"startedDateTime":"2023-02-01T15:31:56.390Z","_requestId":"3504271.42","_initialPriority":"Low","_priority":"Low","pageref":"page_1","request":{"method":"GET","url":"https://quic.totto.page/js/22k.js","queryString":[],"headersSize":-1,"bodySize":0,"cookies":[],"headers":[{"name":"sec-ch-ua","value":""},{"name":"Referer","value":"https://quic.totto.page/single.html"},{"name":"sec-ch-ua-mobile","value":"?0"},{"name":"User-Agent","value":"Mozilla/5.0 (X11; Linux x86_64) AppleWebKit/537.36 (KHTML, like Gecko) HeadlessChrome/109.0.5414.74 Safari/537.36"},{"name":"sec-ch-ua-platform","value":""}],"httpVersion":"h3"},"time":109.435,"_initiator_detail":"{\"type\":\"parser\",\"url\":\"https://quic.totto.page/single.html\",\"lineNumber\":52,\"columnNumber\":33}","_initiator_type":"parser","_initiator":"https://quic.totto.page/single.html","_initiator_line":53,"response":{"httpVersion":"h3","redirectURL":"","status":200,"statusText":"","content":{"mimeType":"application/javascript","size":23137},"headersSize":-1,"bodySize":23267,"cookies":[],"headers":[{"name":"date","value":"Wed, 01 Feb 2023 15:31:56 GMT"},{"name":"last-modified","value":"Fri, 13 Jan 2023 13:00:52 GMT"},{"name":"server","value":"nginx/1.23.4"},{"name":"accept-ranges","value":"bytes"},{"name":"etag","value":"\"63c15604-5a61\""},{"name":"content-length","value":"23137"},{"name":"content-type","value":"application/javascript"}],"_transferSize":23267},"connection":"0","serverIPAddress":"10.10.0.102","timings":{"blocked":0.644,"dns":-1,"connect":-1,"send":0.366,"wait":23.779,"receive":84.646,"ssl":-1,"_queued":1081.069},"_requestTime":823784.738903},{"cache":{},"startedDateTime":"2023-02-01T15:31:56.405Z","_requestId":"3504271.43","_initialPriority":"Low","_priority":"Low","pageref":"page_1","request":{"method":"GET","url":"https://quic.totto.page/js/24k.js","queryString":[],"headersSize":-1,"bodySize":0,"cookies":[],"headers":[{"name":"sec-ch-ua","value":""},{"name":"Referer","value":"https://quic.totto.page/single.html"},{"name":"sec-ch-ua-mobile","value":"?0"},{"name":"User-Agent","value":"Mozilla/5.0 (X11; Linux x86_64) AppleWebKit/537.36 (KHTML, like Gecko) HeadlessChrome/109.0.5414.74 Safari/537.36"},{"name":"sec-ch-ua-platform","value":""}],"httpVersion":"h3"},"time":117.006,"_initiator_detail":"{\"type\":\"parser\",\"url\":\"https://quic.totto.page/single.html\",\"lineNumber\":53,\"columnNumber\":33}","_initiator_type":"parser","_initiator":"https://quic.totto.page/single.html","_initiator_line":54,"response":{"httpVersion":"h3","redirectURL":"","status":200,"statusText":"","content":{"mimeType":"application/javascript","size":25239},"headersSize":-1,"bodySize":25369,"cookies":[],"headers":[{"name":"date","value":"Wed, 01 Feb 2023 15:31:56 GMT"},{"name":"last-modified","value":"Fri, 13 Jan 2023 13:00:52 GMT"},{"name":"server","value":"nginx/1.23.4"},{"name":"accept-ranges","value":"bytes"},{"name":"etag","value":"\"63c15604-6297\""},{"name":"content-length","value":"25239"},{"name":"content-type","value":"application/javascript"}],"_transferSize":25369},"connection":"0","serverIPAddress":"10.10.0.102","timings":{"blocked":0.87,"dns":-1,"connect":-1,"send":0.359,"wait":25.753,"receive":90.024,"ssl":-1,"_queued":1095.342},"_requestTime":823784.753377},{"cache":{},"startedDateTime":"2023-02-01T15:31:56.427Z","_requestId":"3504271.44","_initialPriority":"Low","_priority":"Low","pageref":"page_1","request":{"method":"GET","url":"https://quic.totto.page/js/26k.js","queryString":[],"headersSize":-1,"bodySize":0,"cookies":[],"headers":[{"name":"sec-ch-ua","value":""},{"name":"Referer","value":"https://quic.totto.page/single.html"},{"name":"sec-ch-ua-mobile","value":"?0"},{"name":"User-Agent","value":"Mozilla/5.0 (X11; Linux x86_64) AppleWebKit/537.36 (KHTML, like Gecko) HeadlessChrome/109.0.5414.74 Safari/537.36"},{"name":"sec-ch-ua-platform","value":""}],"httpVersion":"h3"},"time":127.93199999999999,"_initiator_detail":"{\"type\":\"parser\",\"url\":\"https://quic.totto.page/single.html\",\"lineNumber\":54,\"columnNumber\":33}","_initiator_type":"parser","_initiator":"https://quic.totto.page/single.html","_initiator_line":55,"response":{"httpVersion":"h3","redirectURL":"","status":200,"statusText":"","content":{"mimeType":"application/javascript","size":27339},"headersSize":-1,"bodySize":27469,"cookies":[],"headers":[{"name":"date","value":"Wed, 01 Feb 2023 15:31:56 GMT"},{"name":"last-modified","value":"Fri, 13 Jan 2023 13:00:52 GMT"},{"name":"server","value":"nginx/1.23.4"},{"name":"accept-ranges","value":"bytes"},{"name":"etag","value":"\"63c15604-6acb\""},{"name":"content-length","value":"27339"},{"name":"content-type","value":"application/javascript"}],"_transferSize":27469},"connection":"0","serverIPAddress":"10.10.0.102","timings":{"blocked":0.847,"dns":-1,"connect":-1,"send":0.384,"wait":24.988,"receive":101.713,"ssl":-1,"_queued":1116.659},"_requestTime":823784.774915},{"cache":{},"startedDateTime":"2023-02-01T15:31:56.447Z","_requestId":"3504271.45","_initialPriority":"Low","_priority":"Low","pageref":"page_1","request":{"method":"GET","url":"https://quic.totto.page/js/28k.js","queryString":[],"headersSize":-1,"bodySize":0,"cookies":[],"headers":[{"name":"sec-ch-ua","value":""},{"name":"Referer","value":"https://quic.totto.page/single.html"},{"name":"sec-ch-ua-mobile","value":"?0"},{"name":"User-Agent","value":"Mozilla/5.0 (X11; Linux x86_64) AppleWebKit/537.36 (KHTML, like Gecko) HeadlessChrome/109.0.5414.74 Safari/537.36"},{"name":"sec-ch-ua-platform","value":""}],"httpVersion":"h3"},"time":132.454,"_initiator_detail":"{\"type\":\"parser\",\"url\":\"https://quic.totto.page/single.html\",\"lineNumber\":55,\"columnNumber\":33}","_initiator_type":"parser","_initiator":"https://quic.totto.page/single.html","_initiator_line":56,"response":{"httpVersion":"h3","redirectURL":"","status":200,"statusText":"","content":{"mimeType":"application/javascript","size":29441},"headersSize":-1,"bodySize":29571,"cookies":[],"headers":[{"name":"date","value":"Wed, 01 Feb 2023 15:31:56 GMT"},{"name":"last-modified","value":"Fri, 13 Jan 2023 13:00:52 GMT"},{"name":"server","value":"nginx/1.23.4"},{"name":"accept-ranges","value":"bytes"},{"name":"etag","value":"\"63c15604-7301\""},{"name":"content-length","value":"29441"},{"name":"content-type","value":"application/javascript"}],"_transferSize":29571},"connection":"0","serverIPAddress":"10.10.0.102","timings":{"blocked":0.728,"dns":-1,"connect":-1,"send":0.364,"wait":23.754,"receive":107.608,"ssl":-1,"_queued":1136.547},"_requestTime":823784.795008},{"cache":{},"startedDateTime":"2023-02-01T15:31:56.463Z","_requestId":"3504271.46","_initialPriority":"Low","_priority":"Low","pageref":"page_1","request":{"method":"GET","url":"https://quic.totto.page/js/30k.js","queryString":[],"headersSize":-1,"bodySize":0,"cookies":[],"headers":[{"name":"sec-ch-ua","value":""},{"name":"Referer","value":"https://quic.totto.page/single.html"},{"name":"sec-ch-ua-mobile","value":"?0"},{"name":"User-Agent","value":"Mozilla/5.0 (X11; Linux x86_64) AppleWebKit/537.36 (KHTML, like Gecko) HeadlessChrome/109.0.5414.74 Safari/537.36"},{"name":"sec-ch-ua-platform","value":""}],"httpVersion":"h3"},"time":152.474,"_initiator_detail":"{\"type\":\"parser\",\"url\":\"https://quic.totto.page/single.html\",\"lineNumber\":56,\"columnNumber\":33}","_initiator_type":"parser","_initiator":"https://quic.totto.page/single.html","_initiator_line":57,"response":{"httpVersion":"h3","redirectURL":"","status":200,"statusText":"","content":{"mimeType":"application/javascript","size":31541},"headersSize":-1,"bodySize":31671,"cookies":[],"headers":[{"name":"date","value":"Wed, 01 Feb 2023 15:31:56 GMT"},{"name":"last-modified","value":"Fri, 13 Jan 2023 13:00:52 GMT"},{"name":"server","value":"nginx/1.23.4"},{"name":"accept-ranges","value":"bytes"},{"name":"etag","value":"\"63c15604-7b35\""},{"name":"content-length","value":"31541"},{"name":"content-type","value":"application/javascript"}],"_transferSize":31671},"connection":"0","serverIPAddress":"10.10.0.102","timings":{"blocked":0.831,"dns":-1,"connect":-1,"send":0.412,"wait":24.25,"receive":126.981,"ssl":-1,"_queued":1152.893},"_requestTime":823784.811556},{"cache":{},"startedDateTime":"2023-02-01T15:31:56.475Z","_requestId":"3504271.47","_initialPriority":"Low","_priority":"Low","pageref":"page_1","request":{"method":"GET","url":"https://quic.totto.page/js/32k.js","queryString":[],"headersSize":-1,"bodySize":0,"cookies":[],"headers":[{"name":"sec-ch-ua","value":""},{"name":"Referer","value":"https://quic.totto.page/single.html"},{"name":"sec-ch-ua-mobile","value":"?0"},{"name":"User-Agent","value":"Mozilla/5.0 (X11; Linux x86_64) AppleWebKit/537.36 (KHTML, like Gecko) HeadlessChrome/109.0.5414.74 Safari/537.36"},{"name":"sec-ch-ua-platform","value":""}],"httpVersion":"h3"},"time":158.69299999999998,"_initiator_detail":"{\"type\":\"parser\",\"url\":\"https://quic.totto.page/single.html\",\"lineNumber\":57,\"columnNumber\":33}","_initiator_type":"parser","_initiator":"https://quic.totto.page/single.html","_initiator_line":58,"response":{"httpVersion":"h3","redirectURL":"","status":200,"statusText":"","content":{"mimeType":"application/javascript","size":33643},"headersSize":-1,"bodySize":33773,"cookies":[],"headers":[{"name":"date","value":"Wed, 01 Feb 2023 15:31:56 GMT"},{"name":"last-modified","value":"Fri, 13 Jan 2023 13:00:52 GMT"},{"name":"server","value":"nginx/1.23.4"},{"name":"accept-ranges","value":"bytes"},{"name":"etag","value":"\"63c15604-836b\""},{"name":"content-length","value":"33643"},{"name":"content-type","value":"application/javascript"}],"_transferSize":33773},"connection":"0","serverIPAddress":"10.10.0.102","timings":{"blocked":0.624,"dns":-1,"connect":-1,"send":0.384,"wait":26.269,"receive":131.416,"ssl":-1,"_queued":1164.986},"_requestTime":823784.823869},{"cache":{},"startedDateTime":"2023-02-01T15:31:56.500Z","_requestId":"3504271.48","_initialPriority":"Low","_priority":"Low","pageref":"page_1","request":{"method":"GET","url":"https://quic.totto.page/js/34k.js","queryString":[],"headersSize":-1,"bodySize":0,"cookies":[],"headers":[{"name":"sec-ch-ua","value":""},{"name":"Referer","value":"https://quic.totto.page/single.html"},{"name":"sec-ch-ua-mobile","value":"?0"},{"name":"User-Agent","value":"Mozilla/5.0 (X11; Linux x86_64) AppleWebKit/537.36 (KHTML, like Gecko) HeadlessChrome/109.0.5414.74 Safari/537.36"},{"name":"sec-ch-ua-platform","value":""}],"httpVersion":"h3"},"time":160.275,"_initiator_detail":"{\"type\":\"parser\",\"url\":\"https://quic.totto.page/single.html\",\"lineNumber\":58,\"columnNumber\":33}","_initiator_type":"parser","_initiator":"https://quic.totto.page/single.html","_initiator_line":59,"response":{"httpVersion":"h3","redirectURL":"","status":200,"statusText":"","content":{"mimeType":"application/javascript","size":35745},"headersSize":-1,"bodySize":35875,"cookies":[],"headers":[{"name":"date","value":"Wed, 01 Feb 2023 15:31:56 GMT"},{"name":"last-modified","value":"Fri, 13 Jan 2023 13:00:52 GMT"},{"name":"server","value":"nginx/1.23.4"},{"name":"accept-ranges","value":"bytes"},{"name":"etag","value":"\"63c15604-8ba1\""},{"name":"content-length","value":"35745"},{"name":"content-type","value":"application/javascript"}],"_transferSize":35875},"connection":"0","serverIPAddress":"10.10.0.102","timings":{"blocked":0.64,"dns":-1,"connect":-1,"send":0.385,"wait":27.375,"receive":131.875,"ssl":-1,"_queued":1189.619},"_requestTime":823784.848703},{"cache":{},"startedDateTime":"2023-02-01T15:31:56.522Z","_requestId":"3504271.49","_initialPriority":"Low","_priority":"Low","pageref":"page_1","request":{"method":"GET","url":"https://quic.totto.page/js/36k.js","queryString":[],"headersSize":-1,"bodySize":0,"cookies":[],"headers":[{"name":"sec-ch-ua","value":""},{"name":"Referer","value":"https://quic.totto.page/single.html"},{"name":"sec-ch-ua-mobile","value":"?0"},{"name":"User-Agent","value":"Mozilla/5.0 (X11; Linux x86_64) AppleWebKit/537.36 (KHTML, like Gecko) HeadlessChrome/109.0.5414.74 Safari/537.36"},{"name":"sec-ch-ua-platform","value":""}],"httpVersion":"h3"},"time":157.61599999999999,"_initiator_detail":"{\"type\":\"parser\",\"url\":\"https://quic.totto.page/single.html\",\"lineNumber\":59,\"columnNumber\":33}","_initiator_type":"parser","_initiator":"https://quic.totto.page/single.html","_initiator_line":60,"response":{"httpVersion":"h3","redirectURL":"","status":200,"statusText":"","content":{"mimeType":"application/javascript","size":37845},"headersSize":-1,"bodySize":37975,"cookies":[],"headers":[{"name":"date","value":"Wed, 01 Feb 2023 15:31:56 GMT"},{"name":"last-modified","value":"Fri, 13 Jan 2023 13:00:52 GMT"},{"name":"server","value":"nginx/1.23.4"},{"name":"accept-ranges","value":"bytes"},{"name":"etag","value":"\"63c15604-93d5\""},{"name":"content-length","value":"37845"},{"name":"content-type","value":"application/javascript"}],"_transferSize":37975},"connection":"0","serverIPAddress":"10.10.0.102","timings":{"blocked":0.649,"dns":-1,"connect":-1,"send":0.354,"wait":27.549,"receive":129.064,"ssl":-1,"_queued":1211.499},"_requestTime":823784.870789},{"cache":{},"startedDateTime":"2023-02-01T15:31:56.555Z","_requestId":"3504271.50","_initialPriority":"Low","_priority":"Low","pageref":"page_1","request":{"method":"GET","url":"https://quic.totto.page/js/38k.js","queryString":[],"headersSize":-1,"bodySize":0,"cookies":[],"headers":[{"name":"sec-ch-ua","value":""},{"name":"Referer","value":"https://quic.totto.page/single.html"},{"name":"sec-ch-ua-mobile","value":"?0"},{"name":"User-Agent","value":"Mozilla/5.0 (X11; Linux x86_64) AppleWebKit/537.36 (KHTML, like Gecko) HeadlessChrome/109.0.5414.74 Safari/537.36"},{"name":"sec-ch-ua-platform","value":""}],"httpVersion":"h3"},"time":140.027,"_initiator_detail":"{\"type\":\"parser\",\"url\":\"https://quic.totto.page/single.html\",\"lineNumber\":60,\"columnNumber\":33}","_initiator_type":"parser","_initiator":"https://quic.totto.page/single.html","_initiator_line":61,"response":{"httpVersion":"h3","redirectURL":"","status":200,"statusText":"","content":{"mimeType":"application/javascript","size":39947},"headersSize":-1,"bodySize":40077,"cookies":[],"headers":[{"name":"date","value":"Wed, 01 Feb 2023 15:31:56 GMT"},{"name":"last-modified","value":"Fri, 13 Jan 2023 13:00:52 GMT"},{"name":"server","value":"nginx/1.23.4"},{"name":"accept-ranges","value":"bytes"},{"name":"etag","value":"\"63c15604-9c0b\""},{"name":"content-length","value":"39947"},{"name":"content-type","value":"application/javascript"}],"_transferSize":40077},"connection":"0","serverIPAddress":"10.10.0.102","timings":{"blocked":0.825,"dns":-1,"connect":-1,"send":0.381,"wait":30.361,"receive":108.46,"ssl":-1,"_queued":1243.731},"_requestTime":823784.903216},{"cache":{},"startedDateTime":"2023-02-01T15:31:56.579Z","_requestId":"3504271.51","_initialPriority":"Low","_priority":"Low","pageref":"page_1","request":{"method":"GET","url":"https://quic.totto.page/js/40k.js","queryString":[],"headersSize":-1,"bodySize":0,"cookies":[],"headers":[{"name":"sec-ch-ua","value":""},{"name":"Referer","value":"https://quic.totto.page/single.html"},{"name":"sec-ch-ua-mobile","value":"?0"},{"name":"User-Agent","value":"Mozilla/5.0 (X11; Linux x86_64) AppleWebKit/537.36 (KHTML, like Gecko) HeadlessChrome/109.0.5414.74 Safari/537.36"},{"name":"sec-ch-ua-platform","value":""}],"httpVersion":"h3"},"time":125.07600000000001,"_initiator_detail":"{\"type\":\"parser\",\"url\":\"https://quic.totto.page/single.html\",\"lineNumber\":61,\"columnNumber\":33}","_initiator_type":"parser","_initiator":"https://quic.totto.page/single.html","_initiator_line":62,"response":{"httpVersion":"h3","redirectURL":"","status":200,"statusText":"","content":{"mimeType":"application/javascript","size":42047},"headersSize":-1,"bodySize":42177,"cookies":[],"headers":[{"name":"date","value":"Wed, 01 Feb 2023 15:31:56 GMT"},{"name":"last-modified","value":"Fri, 13 Jan 2023 13:00:52 GMT"},{"name":"server","value":"nginx/1.23.4"},{"name":"accept-ranges","value":"bytes"},{"name":"etag","value":"\"63c15604-a43f\""},{"name":"content-length","value":"42047"},{"name":"content-type","value":"application/javascript"}],"_transferSize":42177},"connection":"0","serverIPAddress":"10.10.0.102","timings":{"blocked":0.624,"dns":-1,"connect":-1,"send":0.404,"wait":27.654,"receive":96.394,"ssl":-1,"_queued":1268.157},"_requestTime":823784.927827}]}}}