{"number":997,"start":1675586801454.9,"entries":[{"name":"https://site.totto.page/simple.html","entryType":"navigation","startTime":0,"duration":160.7000000178814,"initiatorType":"navigation","nextHopProtocol":"h2","renderBlockingStatus":"blocking","workerStart":0,"redirectStart":0,"redirectEnd":0,"fetchStart":0.10000002384185791,"domainLookupStart":1.300000011920929,"domainLookupEnd":2.100000023841858,"connectStart":2.100000023841858,"connectEnd":82,"secureConnectionStart":33.5,"requestStart":82.30000001192093,"responseStart":129.10000002384186,"responseEnd":132.30000001192093,"transferSize":1146,"encodedBodySize":846,"decodedBodySize":1613,"responseStatus":0,"serverTiming":[],"unloadEventStart":0,"unloadEventEnd":0,"domInteractive":158.80000001192093,"domContentLoadedEventStart":158.80000001192093,"domContentLoadedEventEnd":160.60000002384186,"domComplete":160.7000000178814,"loadEventStart":160.7000000178814,"loadEventEnd":160.7000000178814,"type":"navigate","redirectCount":0,"activationStart":0}]}